{
  "generated_at": "2026-05-10T09:26:24.783188+02:00",
  "timezone": "Europe/Ljubljana",
  "source": "API-Tennis",
  "model": "AI77 Tennis Totals Value Model v1",
  "stake_mode": "quality_based",
  "market": "Over/Under by Games in Match",
  "filters": {
    "days_ahead": 1,
    "max_picks": 20,
    "max_over_picks": 10,
    "max_under_picks": 10,
    "min_recent_matches_each": 6,
    "min_bookmakers": 5,
    "min_edge": 0.055,
    "min_confidence": 68.0,
    "odds_min": 1.65,
    "odds_max": 2.2,
    "main_lines_min": 18.5,
    "main_lines_max": 24.5,
    "model_prob_min": 0.43,
    "model_prob_max": 0.62
  },
  "summary": {
    "fixtures_checked": 126,
    "candidates_raw": 11,
    "final_picks": 10,
    "errors": 0
  },
  "picks": [
    {
      "pick_id": "74e7e91ea4a7d6d97b3c82bb9e9b8058",
      "event_key": 12125950,
      "fixture_id": 12125950,
      "sport": "tennis",
      "model_version": "ai77_tennis_totals_v1",
      "date": "2026-05-10",
      "time": "11:00",
      "match": "M. Keys - N. Bartunkova",
      "bet": "OVER 20.5 games",
      "bucket": "total_games",
      "side": "over",
      "market": "Over/Under by Games in Match",
      "line": 20.5,
      "first_player_key": 2692,
      "second_player_key": 9196,
      "first_player_name": "M. Keys",
      "second_player_name": "N. Bartunkova",
      "tournament": "Rome",
      "tournament_key": 2010,
      "round": "WTA Rome - 1/16-finals",
      "event_type": "Wta Singles",
      "qualification": false,
      "tour_level": "wta",
      "gender": "women",
      "odds": 1.98,
      "best_bookmaker": "Betano",
      "market_median_odds": 1.9,
      "bookmakers_used": 9,
      "model_prob": 0.62,
      "implied_prob": 0.5051,
      "edge": 0.1149,
      "expected_total_games": 22.15,
      "expected_margin": 1.65,
      "confidence": 89.3,
      "quality_score": 89.2,
      "stake": 1.0,
      "stake_label": "Top Rated",
      "market_info": {
        "home_median_odds": 1.33,
        "away_median_odds": 3.3,
        "home_implied": 0.7519,
        "away_implied": 0.303,
        "market_gap": 0.4488,
        "market_favorite_side": "home"
      },
      "first_form": {
        "last_5": {
          "matches": 5,
          "avg_total_games": 21.8,
          "median_total_games": 20,
          "over_21_5_rate": 0.4,
          "over_22_5_rate": 0.4,
          "three_set_rate": 0.4,
          "straight_set_rate": 0.6,
          "close_set_rate": 0.4,
          "avg_set_diff": 0.8,
          "avg_game_diff": 3.0,
          "win_rate": 0.8
        },
        "last_10": {
          "matches": 10,
          "avg_total_games": 21.5,
          "median_total_games": 19.5,
          "over_21_5_rate": 0.4,
          "over_22_5_rate": 0.4,
          "three_set_rate": 0.4,
          "straight_set_rate": 0.6,
          "close_set_rate": 0.3667,
          "avg_set_diff": 0.4,
          "avg_game_diff": 1.7,
          "win_rate": 0.6
        },
        "last_20": {
          "matches": 10,
          "avg_total_games": 21.5,
          "median_total_games": 19.5,
          "over_21_5_rate": 0.4,
          "over_22_5_rate": 0.4,
          "three_set_rate": 0.4,
          "straight_set_rate": 0.6,
          "close_set_rate": 0.3667,
          "avg_set_diff": 0.4,
          "avg_game_diff": 1.7,
          "win_rate": 0.6
        }
      },
      "second_form": {
        "last_5": {
          "matches": 5,
          "avg_total_games": 24.8,
          "median_total_games": 27,
          "over_21_5_rate": 0.8,
          "over_22_5_rate": 0.8,
          "three_set_rate": 0.8,
          "straight_set_rate": 0.2,
          "close_set_rate": 0.3333,
          "avg_set_diff": 0.4,
          "avg_game_diff": 0.4,
          "win_rate": 0.6
        },
        "last_10": {
          "matches": 8,
          "avg_total_games": 24.62,
          "median_total_games": 27.0,
          "over_21_5_rate": 0.75,
          "over_22_5_rate": 0.75,
          "three_set_rate": 0.75,
          "straight_set_rate": 0.25,
          "close_set_rate": 0.25,
          "avg_set_diff": 0.25,
          "avg_game_diff": 0.625,
          "win_rate": 0.5
        },
        "last_20": {
          "matches": 8,
          "avg_total_games": 24.62,
          "median_total_games": 27.0,
          "over_21_5_rate": 0.75,
          "over_22_5_rate": 0.75,
          "three_set_rate": 0.75,
          "straight_set_rate": 0.25,
          "close_set_rate": 0.25,
          "avg_set_diff": 0.25,
          "avg_game_diff": 0.625,
          "win_rate": 0.5
        }
      },
      "first_strength_score": 62.4,
      "second_strength_score": 53.62,
      "h2h_matches": 0,
      "result": "pending",
      "created_at": "2026-05-10T09:25:06.919684+02:00",
      "reasoning": "OVER 20.5 games selected in M. Keys - N. Bartunkova at line 20.5. Model expected total games: 22.15; market line: 20.5. Model probability 62.0% versus implied 50.5% from best odds 1.98. Edge: +11.5%. Bookmakers used: 9. Confidence: 89.3."
    },
    {
      "pick_id": "0b88cbe27df5d93afe385bb43d35b184",
      "event_key": 12126010,
      "fixture_id": 12126010,
      "sport": "tennis",
      "model_version": "ai77_tennis_totals_v1",
      "date": "2026-05-10",
      "time": "12:30",
      "match": "U. Humbert - D. Prizmic",
      "bet": "UNDER 21.5 games",
      "bucket": "total_games",
      "side": "under",
      "market": "Over/Under by Games in Match",
      "line": 21.5,
      "first_player_key": 1105,
      "second_player_key": 10869,
      "first_player_name": "U. Humbert",
      "second_player_name": "D. Prizmic",
      "tournament": "Rome",
      "tournament_key": 2011,
      "round": "ATP Rome - 1/16-finals",
      "event_type": "Atp Singles",
      "qualification": false,
      "tour_level": "atp",
      "gender": "men",
      "odds": 2.14,
      "best_bookmaker": "Pncl",
      "market_median_odds": 2.055,
      "bookmakers_used": 6,
      "model_prob": 0.57,
      "implied_prob": 0.4673,
      "edge": 0.1027,
      "expected_total_games": 16.5,
      "expected_margin": -5.0,
      "confidence": 88.1,
      "quality_score": 82.9,
      "stake": 0.75,
      "stake_label": "Strong",
      "market_info": {
        "home_median_odds": 2.98,
        "away_median_odds": 1.4,
        "home_implied": 0.3356,
        "away_implied": 0.7143,
        "market_gap": 0.3787,
        "market_favorite_side": "away"
      },
      "first_form": {
        "last_5": {
          "matches": 5,
          "avg_total_games": 19.6,
          "median_total_games": 19,
          "over_21_5_rate": 0.2,
          "over_22_5_rate": 0.2,
          "three_set_rate": 0.0,
          "straight_set_rate": 1.0,
          "close_set_rate": 0.4,
          "avg_set_diff": -0.4,
          "avg_game_diff": -0.8,
          "win_rate": 0.4
        },
        "last_10": {
          "matches": 6,
          "avg_total_games": 19.17,
          "median_total_games": 18.0,
          "over_21_5_rate": 0.1667,
          "over_22_5_rate": 0.1667,
          "three_set_rate": 0.0,
          "straight_set_rate": 1.0,
          "close_set_rate": 0.4167,
          "avg_set_diff": 0.0,
          "avg_game_diff": 0.5,
          "win_rate": 0.5
        },
        "last_20": {
          "matches": 6,
          "avg_total_games": 19.17,
          "median_total_games": 18.0,
          "over_21_5_rate": 0.1667,
          "over_22_5_rate": 0.1667,
          "three_set_rate": 0.0,
          "straight_set_rate": 1.0,
          "close_set_rate": 0.4167,
          "avg_set_diff": 0.0,
          "avg_game_diff": 0.5,
          "win_rate": 0.5
        }
      },
      "second_form": {
        "last_5": {
          "matches": 5,
          "avg_total_games": 21.8,
          "median_total_games": 19,
          "over_21_5_rate": 0.4,
          "over_22_5_rate": 0.4,
          "three_set_rate": 0.4,
          "straight_set_rate": 0.6,
          "close_set_rate": 0.4333,
          "avg_set_diff": 1.2,
          "avg_game_diff": 3.4,
          "win_rate": 0.8
        },
        "last_10": {
          "matches": 7,
          "avg_total_games": 20.71,
          "median_total_games": 19,
          "over_21_5_rate": 0.2857,
          "over_22_5_rate": 0.2857,
          "three_set_rate": 0.2857,
          "straight_set_rate": 0.7143,
          "close_set_rate": 0.381,
          "avg_set_diff": 1.429,
          "avg_game_diff": 4.143,
          "win_rate": 0.8571
        },
        "last_20": {
          "matches": 7,
          "avg_total_games": 20.71,
          "median_total_games": 19,
          "over_21_5_rate": 0.2857,
          "over_22_5_rate": 0.2857,
          "three_set_rate": 0.2857,
          "straight_set_rate": 0.7143,
          "close_set_rate": 0.381,
          "avg_set_diff": 1.429,
          "avg_game_diff": 4.143,
          "win_rate": 0.8571
        }
      },
      "first_strength_score": 51.5,
      "second_strength_score": 88.5,
      "h2h_matches": 0,
      "result": "pending",
      "created_at": "2026-05-10T09:25:17.828220+02:00",
      "reasoning": "UNDER 21.5 games selected in U. Humbert - D. Prizmic at line 21.5. Model expected total games: 16.50; market line: 21.5. Model probability 57.0% versus implied 46.7% from best odds 2.14. Edge: +10.3%. Bookmakers used: 6. Confidence: 88.1."
    },
    {
      "pick_id": "d472f522009ac4f9d1bcda9cc870424e",
      "event_key": 12125918,
      "fixture_id": 12125918,
      "sport": "tennis",
      "model_version": "ai77_tennis_totals_v1",
      "date": "2026-05-10",
      "time": "12:30",
      "match": "L. Samsonova - A. Potapova",
      "bet": "UNDER 20.5 games",
      "bucket": "total_games",
      "side": "under",
      "market": "Over/Under by Games in Match",
      "line": 20.5,
      "first_player_key": 68376,
      "second_player_key": 457,
      "first_player_name": "L. Samsonova",
      "second_player_name": "A. Potapova",
      "tournament": "Rome",
      "tournament_key": 2010,
      "round": "WTA Rome - 1/16-finals",
      "event_type": "Wta Singles",
      "qualification": false,
      "tour_level": "wta",
      "gender": "women",
      "odds": 2.1,
      "best_bookmaker": "Betano",
      "market_median_odds": 2.06,
      "bookmakers_used": 6,
      "model_prob": 0.57,
      "implied_prob": 0.4762,
      "edge": 0.0938,
      "expected_total_games": 17.72,
      "expected_margin": -2.78,
      "confidence": 86.5,
      "quality_score": 81.9,
      "stake": 0.75,
      "stake_label": "Strong",
      "market_info": {
        "home_median_odds": 2.38,
        "away_median_odds": 1.565,
        "home_implied": 0.4202,
        "away_implied": 0.639,
        "market_gap": 0.2188,
        "market_favorite_side": "away"
      },
      "first_form": {
        "last_5": {
          "matches": 5,
          "avg_total_games": 18.0,
          "median_total_games": 19,
          "over_21_5_rate": 0.0,
          "over_22_5_rate": 0.0,
          "three_set_rate": 0.0,
          "straight_set_rate": 1.0,
          "close_set_rate": 0.4,
          "avg_set_diff": 0.4,
          "avg_game_diff": 2.0,
          "win_rate": 0.6
        },
        "last_10": {
          "matches": 9,
          "avg_total_games": 22.11,
          "median_total_games": 19,
          "over_21_5_rate": 0.3333,
          "over_22_5_rate": 0.3333,
          "three_set_rate": 0.3333,
          "straight_set_rate": 0.6667,
          "close_set_rate": 0.463,
          "avg_set_diff": -0.111,
          "avg_game_diff": -0.111,
          "win_rate": 0.3333
        },
        "last_20": {
          "matches": 9,
          "avg_total_games": 22.11,
          "median_total_games": 19,
          "over_21_5_rate": 0.3333,
          "over_22_5_rate": 0.3333,
          "three_set_rate": 0.3333,
          "straight_set_rate": 0.6667,
          "close_set_rate": 0.463,
          "avg_set_diff": -0.111,
          "avg_game_diff": -0.111,
          "win_rate": 0.3333
        }
      },
      "second_form": {
        "last_5": {
          "matches": 5,
          "avg_total_games": 23.2,
          "median_total_games": 22,
          "over_21_5_rate": 0.6,
          "over_22_5_rate": 0.4,
          "three_set_rate": 0.6,
          "straight_set_rate": 0.4,
          "close_set_rate": 0.3667,
          "avg_set_diff": 1.0,
          "avg_game_diff": 3.6,
          "win_rate": 0.8
        },
        "last_10": {
          "matches": 9,
          "avg_total_games": 21.67,
          "median_total_games": 19,
          "over_21_5_rate": 0.4444,
          "over_22_5_rate": 0.3333,
          "three_set_rate": 0.4444,
          "straight_set_rate": 0.5556,
          "close_set_rate": 0.3148,
          "avg_set_diff": 0.889,
          "avg_game_diff": 3.222,
          "win_rate": 0.7778
        },
        "last_20": {
          "matches": 9,
          "avg_total_games": 21.67,
          "median_total_games": 19,
          "over_21_5_rate": 0.4444,
          "over_22_5_rate": 0.3333,
          "three_set_rate": 0.4444,
          "straight_set_rate": 0.5556,
          "close_set_rate": 0.3148,
          "avg_set_diff": 0.889,
          "avg_game_diff": 3.222,
          "win_rate": 0.7778
        }
      },
      "first_strength_score": 41.39,
      "second_strength_score": 78.39,
      "h2h_matches": 0,
      "result": "pending",
      "created_at": "2026-05-10T09:24:59.124490+02:00",
      "reasoning": "UNDER 20.5 games selected in L. Samsonova - A. Potapova at line 20.5. Model expected total games: 17.72; market line: 20.5. Model probability 57.0% versus implied 47.6% from best odds 2.10. Edge: +9.4%. Bookmakers used: 6. Confidence: 86.5."
    },
    {
      "pick_id": "05f09eec465aaf5e9875c81484095263",
      "event_key": 12125951,
      "fixture_id": 12125951,
      "sport": "tennis",
      "model_version": "ai77_tennis_totals_v1",
      "date": "2026-05-10",
      "time": "11:00",
      "match": "E. Svitolina - H. Baptiste",
      "bet": "UNDER 20.5 games",
      "bucket": "total_games",
      "side": "under",
      "market": "Over/Under by Games in Match",
      "line": 20.5,
      "first_player_key": 2816,
      "second_player_key": 490,
      "first_player_name": "E. Svitolina",
      "second_player_name": "H. Baptiste",
      "tournament": "Rome",
      "tournament_key": 2010,
      "round": "WTA Rome - 1/16-finals",
      "event_type": "Wta Singles",
      "qualification": false,
      "tour_level": "wta",
      "gender": "women",
      "odds": 2.13,
      "best_bookmaker": "Pncl",
      "market_median_odds": 2.02,
      "bookmakers_used": 7,
      "model_prob": 0.57,
      "implied_prob": 0.4695,
      "edge": 0.1005,
      "expected_total_games": 18.66,
      "expected_margin": -1.84,
      "confidence": 80.4,
      "quality_score": 80.2,
      "stake": 0.75,
      "stake_label": "Strong",
      "market_info": {
        "home_median_odds": 1.44,
        "away_median_odds": 2.75,
        "home_implied": 0.6944,
        "away_implied": 0.3636,
        "market_gap": 0.3308,
        "market_favorite_side": "home"
      },
      "first_form": {
        "last_5": {
          "matches": 5,
          "avg_total_games": 18.2,
          "median_total_games": 16,
          "over_21_5_rate": 0.2,
          "over_22_5_rate": 0.2,
          "three_set_rate": 0.2,
          "straight_set_rate": 0.8,
          "close_set_rate": 0.2333,
          "avg_set_diff": 0.6,
          "avg_game_diff": 4.6,
          "win_rate": 0.6
        },
        "last_10": {
          "matches": 9,
          "avg_total_games": 20.0,
          "median_total_games": 19,
          "over_21_5_rate": 0.3333,
          "over_22_5_rate": 0.2222,
          "three_set_rate": 0.2222,
          "straight_set_rate": 0.7778,
          "close_set_rate": 0.4259,
          "avg_set_diff": 0.222,
          "avg_game_diff": 2.667,
          "win_rate": 0.5556
        },
        "last_20": {
          "matches": 9,
          "avg_total_games": 20.0,
          "median_total_games": 19,
          "over_21_5_rate": 0.3333,
          "over_22_5_rate": 0.2222,
          "three_set_rate": 0.2222,
          "straight_set_rate": 0.7778,
          "close_set_rate": 0.4259,
          "avg_set_diff": 0.222,
          "avg_game_diff": 2.667,
          "win_rate": 0.5556
        }
      },
      "second_form": {
        "last_5": {
          "matches": 5,
          "avg_total_games": 18.0,
          "median_total_games": 17,
          "over_21_5_rate": 0.0,
          "over_22_5_rate": 0.0,
          "three_set_rate": 0.0,
          "straight_set_rate": 1.0,
          "close_set_rate": 0.4,
          "avg_set_diff": 1.6,
          "avg_game_diff": 4.8,
          "win_rate": 1.0
        },
        "last_10": {
          "matches": 9,
          "avg_total_games": 20.56,
          "median_total_games": 20,
          "over_21_5_rate": 0.2222,
          "over_22_5_rate": 0.2222,
          "three_set_rate": 0.2222,
          "straight_set_rate": 0.7778,
          "close_set_rate": 0.4074,
          "avg_set_diff": 0.444,
          "avg_game_diff": 1.667,
          "win_rate": 0.6667
        },
        "last_20": {
          "matches": 9,
          "avg_total_games": 20.56,
          "median_total_games": 20,
          "over_21_5_rate": 0.2222,
          "over_22_5_rate": 0.2222,
          "three_set_rate": 0.2222,
          "straight_set_rate": 0.7778,
          "close_set_rate": 0.4074,
          "avg_set_diff": 0.444,
          "avg_game_diff": 1.667,
          "win_rate": 0.6667
        }
      },
      "first_strength_score": 62.06,
      "second_strength_score": 65.61,
      "h2h_matches": 1,
      "result": "pending",
      "created_at": "2026-05-10T09:25:08.457348+02:00",
      "reasoning": "UNDER 20.5 games selected in E. Svitolina - H. Baptiste at line 20.5. Model expected total games: 18.66; market line: 20.5. Model probability 57.0% versus implied 46.9% from best odds 2.13. Edge: +10.1%. Bookmakers used: 7. Confidence: 80.4."
    },
    {
      "pick_id": "89a28b97e74bf45d578e45f7b9428cff",
      "event_key": 12125922,
      "fixture_id": 12125922,
      "sport": "tennis",
      "model_version": "ai77_tennis_totals_v1",
      "date": "2026-05-10",
      "time": "14:00",
      "match": "K. Khachanov - B. Van De Zandschulp",
      "bet": "UNDER 22.5 games",
      "bucket": "total_games",
      "side": "under",
      "market": "Over/Under by Games in Match",
      "line": 22.5,
      "first_player_key": 435,
      "second_player_key": 2972,
      "first_player_name": "K. Khachanov",
      "second_player_name": "B. Van De Zandschulp",
      "tournament": "Rome",
      "tournament_key": 2011,
      "round": "ATP Rome - 1/16-finals",
      "event_type": "Atp Singles",
      "qualification": false,
      "tour_level": "atp",
      "gender": "men",
      "odds": 2.05,
      "best_bookmaker": "Betano",
      "market_median_odds": 1.99,
      "bookmakers_used": 6,
      "model_prob": 0.57,
      "implied_prob": 0.4878,
      "edge": 0.0822,
      "expected_total_games": 18.07,
      "expected_margin": -4.43,
      "confidence": 90.1,
      "quality_score": 80.0,
      "stake": 0.75,
      "stake_label": "Strong",
      "market_info": {
        "home_median_odds": 1.67,
        "away_median_odds": 2.2,
        "home_implied": 0.5988,
        "away_implied": 0.4545,
        "market_gap": 0.1443,
        "market_favorite_side": "home"
      },
      "first_form": {
        "last_5": {
          "matches": 5,
          "avg_total_games": 18.8,
          "median_total_games": 19,
          "over_21_5_rate": 0.0,
          "over_22_5_rate": 0.0,
          "three_set_rate": 0.0,
          "straight_set_rate": 1.0,
          "close_set_rate": 0.4,
          "avg_set_diff": 0.4,
          "avg_game_diff": 1.2,
          "win_rate": 0.6
        },
        "last_10": {
          "matches": 6,
          "avg_total_games": 19.0,
          "median_total_games": 19.5,
          "over_21_5_rate": 0.0,
          "over_22_5_rate": 0.0,
          "three_set_rate": 0.0,
          "straight_set_rate": 1.0,
          "close_set_rate": 0.5,
          "avg_set_diff": 0.333,
          "avg_game_diff": 1.0,
          "win_rate": 0.5
        },
        "last_20": {
          "matches": 6,
          "avg_total_games": 19.0,
          "median_total_games": 19.5,
          "over_21_5_rate": 0.0,
          "over_22_5_rate": 0.0,
          "three_set_rate": 0.0,
          "straight_set_rate": 1.0,
          "close_set_rate": 0.5,
          "avg_set_diff": 0.333,
          "avg_game_diff": 1.0,
          "win_rate": 0.5
        }
      },
      "second_form": {
        "last_5": {
          "matches": 5,
          "avg_total_games": 18.8,
          "median_total_games": 18,
          "over_21_5_rate": 0.2,
          "over_22_5_rate": 0.2,
          "three_set_rate": 0.0,
          "straight_set_rate": 1.0,
          "close_set_rate": 0.3,
          "avg_set_diff": 0.4,
          "avg_game_diff": 0.4,
          "win_rate": 0.6
        },
        "last_10": {
          "matches": 9,
          "avg_total_games": 18.78,
          "median_total_games": 18,
          "over_21_5_rate": 0.1111,
          "over_22_5_rate": 0.1111,
          "three_set_rate": 0.0,
          "straight_set_rate": 1.0,
          "close_set_rate": 0.2778,
          "avg_set_diff": 0.667,
          "avg_game_diff": 1.667,
          "win_rate": 0.6667
        },
        "last_20": {
          "matches": 9,
          "avg_total_games": 18.78,
          "median_total_games": 18,
          "over_21_5_rate": 0.1111,
          "over_22_5_rate": 0.1111,
          "three_set_rate": 0.0,
          "straight_set_rate": 1.0,
          "close_set_rate": 0.2778,
          "avg_set_diff": 0.667,
          "avg_game_diff": 1.667,
          "win_rate": 0.6667
        }
      },
      "first_strength_score": 55.33,
      "second_strength_score": 67.17,
      "h2h_matches": 2,
      "result": "pending",
      "created_at": "2026-05-10T09:25:05.398711+02:00",
      "reasoning": "UNDER 22.5 games selected in K. Khachanov - B. Van De Zandschulp at line 22.5. Model expected total games: 18.07; market line: 22.5. Model probability 57.0% versus implied 48.8% from best odds 2.05. Edge: +8.2%. Bookmakers used: 6. Confidence: 90.1."
    },
    {
      "pick_id": "7a5f6cf6751fed31845e76a241d42df9",
      "event_key": 12125921,
      "fixture_id": 12125921,
      "sport": "tennis",
      "model_version": "ai77_tennis_totals_v1",
      "date": "2026-05-10",
      "time": "11:00",
      "match": "C. Ruud - J. Lehecka",
      "bet": "UNDER 22.5 games",
      "bucket": "total_games",
      "side": "under",
      "market": "Over/Under by Games in Match",
      "line": 22.5,
      "first_player_key": 430,
      "second_player_key": 2959,
      "first_player_name": "C. Ruud",
      "second_player_name": "J. Lehecka",
      "tournament": "Rome",
      "tournament_key": 2011,
      "round": "ATP Rome - 1/16-finals",
      "event_type": "Atp Singles",
      "qualification": false,
      "tour_level": "atp",
      "gender": "men",
      "odds": 2.0,
      "best_bookmaker": "Pncl",
      "market_median_odds": 1.91,
      "bookmakers_used": 7,
      "model_prob": 0.57,
      "implied_prob": 0.5,
      "edge": 0.07,
      "expected_total_games": 16.5,
      "expected_margin": -6.0,
      "confidence": 90.9,
      "quality_score": 78.0,
      "stake": 0.5,
      "stake_label": "Standard",
      "market_info": {
        "home_median_odds": 1.53,
        "away_median_odds": 2.5,
        "home_implied": 0.6536,
        "away_implied": 0.4,
        "market_gap": 0.2536,
        "market_favorite_side": "home"
      },
      "first_form": {
        "last_5": {
          "matches": 5,
          "avg_total_games": 17.2,
          "median_total_games": 16,
          "over_21_5_rate": 0.0,
          "over_22_5_rate": 0.0,
          "three_set_rate": 0.0,
          "straight_set_rate": 1.0,
          "close_set_rate": 0.3,
          "avg_set_diff": 1.2,
          "avg_game_diff": 5.6,
          "win_rate": 0.8
        },
        "last_10": {
          "matches": 6,
          "avg_total_games": 17.5,
          "median_total_games": 17.5,
          "over_21_5_rate": 0.0,
          "over_22_5_rate": 0.0,
          "three_set_rate": 0.0,
          "straight_set_rate": 1.0,
          "close_set_rate": 0.3333,
          "avg_set_diff": 1.333,
          "avg_game_diff": 5.5,
          "win_rate": 0.8333
        },
        "last_20": {
          "matches": 6,
          "avg_total_games": 17.5,
          "median_total_games": 17.5,
          "over_21_5_rate": 0.0,
          "over_22_5_rate": 0.0,
          "three_set_rate": 0.0,
          "straight_set_rate": 1.0,
          "close_set_rate": 0.3333,
          "avg_set_diff": 1.333,
          "avg_game_diff": 5.5,
          "win_rate": 0.8333
        }
      },
      "second_form": {
        "last_5": {
          "matches": 5,
          "avg_total_games": 18.8,
          "median_total_games": 19,
          "over_21_5_rate": 0.0,
          "over_22_5_rate": 0.0,
          "three_set_rate": 0.0,
          "straight_set_rate": 1.0,
          "close_set_rate": 0.4,
          "avg_set_diff": 0.0,
          "avg_game_diff": 0.0,
          "win_rate": 0.6
        },
        "last_10": {
          "matches": 8,
          "avg_total_games": 18.62,
          "median_total_games": 19.0,
          "over_21_5_rate": 0.0,
          "over_22_5_rate": 0.0,
          "three_set_rate": 0.0,
          "straight_set_rate": 1.0,
          "close_set_rate": 0.4375,
          "avg_set_diff": 0.0,
          "avg_game_diff": 0.625,
          "win_rate": 0.625
        },
        "last_20": {
          "matches": 8,
          "avg_total_games": 18.62,
          "median_total_games": 19.0,
          "over_21_5_rate": 0.0,
          "over_22_5_rate": 0.0,
          "three_set_rate": 0.0,
          "straight_set_rate": 1.0,
          "close_set_rate": 0.4375,
          "avg_set_diff": 0.0,
          "avg_game_diff": 0.625,
          "win_rate": 0.625
        }
      },
      "first_strength_score": 90.83,
      "second_strength_score": 57.5,
      "h2h_matches": 1,
      "result": "pending",
      "created_at": "2026-05-10T09:25:03.843024+02:00",
      "reasoning": "UNDER 22.5 games selected in C. Ruud - J. Lehecka at line 22.5. Model expected total games: 16.50; market line: 22.5. Model probability 57.0% versus implied 50.0% from best odds 2.00. Edge: +7.0%. Bookmakers used: 7. Confidence: 90.9."
    },
    {
      "pick_id": "017ae6877e2e3563a9df7920c9bec0f6",
      "event_key": 12126058,
      "fixture_id": 12126058,
      "sport": "tennis",
      "model_version": "ai77_tennis_totals_v1",
      "date": "2026-05-10",
      "time": "13:00",
      "match": "D. Vekic - M. Timofeeva",
      "bet": "UNDER 20.5 games",
      "bucket": "total_games",
      "side": "under",
      "market": "Over/Under by Games in Match",
      "line": 20.5,
      "first_player_key": 455,
      "second_player_key": 12869,
      "first_player_name": "D. Vekic",
      "second_player_name": "M. Timofeeva",
      "tournament": "Istanbul (Turkey) - Qualification",
      "tournament_key": 13828,
      "round": "Istanbul - Final",
      "event_type": "Challenger Women Singles",
      "qualification": false,
      "tour_level": "challenger",
      "gender": "women",
      "odds": 1.97,
      "best_bookmaker": "Pncl",
      "market_median_odds": 1.87,
      "bookmakers_used": 7,
      "model_prob": 0.57,
      "implied_prob": 0.5076,
      "edge": 0.0624,
      "expected_total_games": 17.11,
      "expected_margin": -3.39,
      "confidence": 90.9,
      "quality_score": 77.7,
      "stake": 0.5,
      "stake_label": "Standard",
      "market_info": {
        "home_median_odds": 1.44,
        "away_median_odds": 2.7,
        "home_implied": 0.6944,
        "away_implied": 0.3704,
        "market_gap": 0.3241,
        "market_favorite_side": "home"
      },
      "first_form": {
        "last_5": {
          "matches": 5,
          "avg_total_games": 19.2,
          "median_total_games": 18,
          "over_21_5_rate": 0.2,
          "over_22_5_rate": 0.2,
          "three_set_rate": 0.2,
          "straight_set_rate": 0.8,
          "close_set_rate": 0.3667,
          "avg_set_diff": 1.4,
          "avg_game_diff": 5.2,
          "win_rate": 0.8
        },
        "last_10": {
          "matches": 10,
          "avg_total_games": 20.2,
          "median_total_games": 18.5,
          "over_21_5_rate": 0.3,
          "over_22_5_rate": 0.2,
          "three_set_rate": 0.2,
          "straight_set_rate": 0.8,
          "close_set_rate": 0.5167,
          "avg_set_diff": 1.0,
          "avg_game_diff": 3.2,
          "win_rate": 0.8
        },
        "last_20": {
          "matches": 10,
          "avg_total_games": 20.2,
          "median_total_games": 18.5,
          "over_21_5_rate": 0.3,
          "over_22_5_rate": 0.2,
          "three_set_rate": 0.2,
          "straight_set_rate": 0.8,
          "close_set_rate": 0.5167,
          "avg_set_diff": 1.0,
          "avg_game_diff": 3.2,
          "win_rate": 0.8
        }
      },
      "second_form": {
        "last_5": {
          "matches": 5,
          "avg_total_games": 19.4,
          "median_total_games": 19,
          "over_21_5_rate": 0.2,
          "over_22_5_rate": 0.2,
          "three_set_rate": 0.2,
          "straight_set_rate": 0.8,
          "close_set_rate": 0.3333,
          "avg_set_diff": 1.8,
          "avg_game_diff": 6.2,
          "win_rate": 1.0
        },
        "last_10": {
          "matches": 8,
          "avg_total_games": 19.25,
          "median_total_games": 18.0,
          "over_21_5_rate": 0.25,
          "over_22_5_rate": 0.25,
          "three_set_rate": 0.25,
          "straight_set_rate": 0.75,
          "close_set_rate": 0.3125,
          "avg_set_diff": 1.5,
          "avg_game_diff": 5.75,
          "win_rate": 1.0
        },
        "last_20": {
          "matches": 8,
          "avg_total_games": 19.25,
          "median_total_games": 18.0,
          "over_21_5_rate": 0.25,
          "over_22_5_rate": 0.25,
          "three_set_rate": 0.25,
          "straight_set_rate": 0.75,
          "close_set_rate": 0.3125,
          "avg_set_diff": 1.5,
          "avg_game_diff": 5.75,
          "win_rate": 1.0
        }
      },
      "first_strength_score": 80.1,
      "second_strength_score": 99,
      "h2h_matches": 0,
      "result": "pending",
      "created_at": "2026-05-10T09:25:35.503346+02:00",
      "reasoning": "UNDER 20.5 games selected in D. Vekic - M. Timofeeva at line 20.5. Model expected total games: 17.11; market line: 20.5. Model probability 57.0% versus implied 50.8% from best odds 1.97. Edge: +6.2%. Bookmakers used: 7. Confidence: 90.9."
    },
    {
      "pick_id": "6a2c0cd9042572011a4ede42c2db8da3",
      "event_key": 12126018,
      "fixture_id": 12126018,
      "sport": "tennis",
      "model_version": "ai77_tennis_totals_v1",
      "date": "2026-05-10",
      "time": "17:30",
      "match": "T. Paul - L. Darderi",
      "bet": "UNDER 22.5 games",
      "bucket": "total_games",
      "side": "under",
      "market": "Over/Under by Games in Match",
      "line": 22.5,
      "first_player_key": 1894,
      "second_player_key": 8781,
      "first_player_name": "T. Paul",
      "second_player_name": "L. Darderi",
      "tournament": "Rome",
      "tournament_key": 2011,
      "round": "ATP Rome - 1/16-finals",
      "event_type": "Atp Singles",
      "qualification": false,
      "tour_level": "atp",
      "gender": "men",
      "odds": 2.0,
      "best_bookmaker": "1xBet",
      "market_median_odds": 1.95,
      "bookmakers_used": 5,
      "model_prob": 0.57,
      "implied_prob": 0.5,
      "edge": 0.07,
      "expected_total_games": 18.54,
      "expected_margin": -3.96,
      "confidence": 89.3,
      "quality_score": 77.6,
      "stake": 0.5,
      "stake_label": "Standard",
      "market_info": {
        "home_median_odds": 1.73,
        "away_median_odds": 2.13,
        "home_implied": 0.578,
        "away_implied": 0.4695,
        "market_gap": 0.1086,
        "market_favorite_side": "home"
      },
      "first_form": {
        "last_5": {
          "matches": 5,
          "avg_total_games": 21.6,
          "median_total_games": 22,
          "over_21_5_rate": 0.6,
          "over_22_5_rate": 0.2,
          "three_set_rate": 0.2,
          "straight_set_rate": 0.8,
          "close_set_rate": 0.6667,
          "avg_set_diff": 0.6,
          "avg_game_diff": 2.4,
          "win_rate": 0.8
        },
        "last_10": {
          "matches": 9,
          "avg_total_games": 21.78,
          "median_total_games": 22,
          "over_21_5_rate": 0.5556,
          "over_22_5_rate": 0.3333,
          "three_set_rate": 0.3333,
          "straight_set_rate": 0.6667,
          "close_set_rate": 0.4815,
          "avg_set_diff": 0.778,
          "avg_game_diff": 2.667,
          "win_rate": 0.8889
        },
        "last_20": {
          "matches": 9,
          "avg_total_games": 21.78,
          "median_total_games": 22,
          "over_21_5_rate": 0.5556,
          "over_22_5_rate": 0.3333,
          "three_set_rate": 0.3333,
          "straight_set_rate": 0.6667,
          "close_set_rate": 0.4815,
          "avg_set_diff": 0.778,
          "avg_game_diff": 2.667,
          "win_rate": 0.8889
        }
      },
      "second_form": {
        "last_5": {
          "matches": 5,
          "avg_total_games": 18.8,
          "median_total_games": 17,
          "over_21_5_rate": 0.2,
          "over_22_5_rate": 0.2,
          "three_set_rate": 0.2,
          "straight_set_rate": 0.8,
          "close_set_rate": 0.2667,
          "avg_set_diff": 0.2,
          "avg_game_diff": 0.8,
          "win_rate": 0.6
        },
        "last_10": {
          "matches": 9,
          "avg_total_games": 19.78,
          "median_total_games": 19,
          "over_21_5_rate": 0.2222,
          "over_22_5_rate": 0.2222,
          "three_set_rate": 0.2222,
          "straight_set_rate": 0.7778,
          "close_set_rate": 0.3889,
          "avg_set_diff": 0.0,
          "avg_game_diff": -0.222,
          "win_rate": 0.4444
        },
        "last_20": {
          "matches": 9,
          "avg_total_games": 19.78,
          "median_total_games": 19,
          "over_21_5_rate": 0.2222,
          "over_22_5_rate": 0.2222,
          "three_set_rate": 0.2222,
          "straight_set_rate": 0.7778,
          "close_set_rate": 0.3889,
          "avg_set_diff": 0.0,
          "avg_game_diff": -0.222,
          "win_rate": 0.4444
        }
      },
      "first_strength_score": 80.95,
      "second_strength_score": 46.83,
      "h2h_matches": 0,
      "result": "pending",
      "created_at": "2026-05-10T09:25:20.897770+02:00",
      "reasoning": "UNDER 22.5 games selected in T. Paul - L. Darderi at line 22.5. Model expected total games: 18.54; market line: 22.5. Model probability 57.0% versus implied 50.0% from best odds 2.00. Edge: +7.0%. Bookmakers used: 5. Confidence: 89.3."
    },
    {
      "pick_id": "d10a4326cb19e2741b24a26eb197f7c8",
      "event_key": 12125969,
      "fixture_id": 12125969,
      "sport": "tennis",
      "model_version": "ai77_tennis_totals_v1",
      "date": "2026-05-10",
      "time": "13:00",
      "match": "A. Blockx - A. Zverev",
      "bet": "UNDER 21.5 games",
      "bucket": "total_games",
      "side": "under",
      "market": "Over/Under by Games in Match",
      "line": 21.5,
      "first_player_key": 39913,
      "second_player_key": 1980,
      "first_player_name": "A. Blockx",
      "second_player_name": "A. Zverev",
      "tournament": "Rome",
      "tournament_key": 2011,
      "round": "ATP Rome - 1/16-finals",
      "event_type": "Atp Singles",
      "qualification": false,
      "tour_level": "atp",
      "gender": "men",
      "odds": 2.08,
      "best_bookmaker": "Pncl",
      "market_median_odds": 2.0,
      "bookmakers_used": 8,
      "model_prob": 0.57,
      "implied_prob": 0.4808,
      "edge": 0.0892,
      "expected_total_games": 20.21,
      "expected_margin": -1.29,
      "confidence": 77.2,
      "quality_score": 73.3,
      "stake": 0.5,
      "stake_label": "Standard",
      "market_info": {
        "home_median_odds": 3.88,
        "away_median_odds": 1.25,
        "home_implied": 0.2577,
        "away_implied": 0.8,
        "market_gap": 0.5423,
        "market_favorite_side": "away"
      },
      "first_form": {
        "last_5": {
          "matches": 5,
          "avg_total_games": 22.6,
          "median_total_games": 20,
          "over_21_5_rate": 0.4,
          "over_22_5_rate": 0.4,
          "three_set_rate": 0.4,
          "straight_set_rate": 0.6,
          "close_set_rate": 0.5333,
          "avg_set_diff": 0.8,
          "avg_game_diff": 2.2,
          "win_rate": 0.8
        },
        "last_10": {
          "matches": 6,
          "avg_total_games": 24.5,
          "median_total_games": 23.0,
          "over_21_5_rate": 0.5,
          "over_22_5_rate": 0.5,
          "three_set_rate": 0.5,
          "straight_set_rate": 0.5,
          "close_set_rate": 0.6111,
          "avg_set_diff": 0.833,
          "avg_game_diff": 2.167,
          "win_rate": 0.8333
        },
        "last_20": {
          "matches": 6,
          "avg_total_games": 24.5,
          "median_total_games": 23.0,
          "over_21_5_rate": 0.5,
          "over_22_5_rate": 0.5,
          "three_set_rate": 0.5,
          "straight_set_rate": 0.5,
          "close_set_rate": 0.6111,
          "avg_set_diff": 0.833,
          "avg_game_diff": 2.167,
          "win_rate": 0.8333
        }
      },
      "second_form": {
        "last_5": {
          "matches": 5,
          "avg_total_games": 18.4,
          "median_total_games": 19,
          "over_21_5_rate": 0.0,
          "over_22_5_rate": 0.0,
          "three_set_rate": 0.0,
          "straight_set_rate": 1.0,
          "close_set_rate": 0.4,
          "avg_set_diff": 1.2,
          "avg_game_diff": 2.8,
          "win_rate": 0.8
        },
        "last_10": {
          "matches": 9,
          "avg_total_games": 19.56,
          "median_total_games": 19,
          "over_21_5_rate": 0.2222,
          "over_22_5_rate": 0.2222,
          "three_set_rate": 0.2222,
          "straight_set_rate": 0.7778,
          "close_set_rate": 0.2593,
          "avg_set_diff": 0.889,
          "avg_game_diff": 3.333,
          "win_rate": 0.7778
        },
        "last_20": {
          "matches": 9,
          "avg_total_games": 19.56,
          "median_total_games": 19,
          "over_21_5_rate": 0.2222,
          "over_22_5_rate": 0.2222,
          "three_set_rate": 0.2222,
          "straight_set_rate": 0.7778,
          "close_set_rate": 0.2593,
          "avg_set_diff": 0.889,
          "avg_game_diff": 3.333,
          "win_rate": 0.7778
        }
      },
      "first_strength_score": 77.33,
      "second_strength_score": 78.72,
      "h2h_matches": 1,
      "result": "pending",
      "created_at": "2026-05-10T09:25:10.053299+02:00",
      "reasoning": "UNDER 21.5 games selected in A. Blockx - A. Zverev at line 21.5. Model expected total games: 20.21; market line: 21.5. Model probability 57.0% versus implied 48.1% from best odds 2.08. Edge: +8.9%. Bookmakers used: 8. Confidence: 77.2."
    },
    {
      "pick_id": "545b2bb5d5a1fd7d49696b41f270b065",
      "event_key": 12125908,
      "fixture_id": 12125908,
      "sport": "tennis",
      "model_version": "ai77_tennis_totals_v1",
      "date": "2026-05-10",
      "time": "20:30",
      "match": "M. Arnaldi - R. Jodar",
      "bet": "UNDER 20.5 games",
      "bucket": "total_games",
      "side": "under",
      "market": "Over/Under by Games in Match",
      "line": 20.5,
      "first_player_key": 1192,
      "second_player_key": 50323,
      "first_player_name": "M. Arnaldi",
      "second_player_name": "R. Jodar",
      "tournament": "Rome",
      "tournament_key": 2011,
      "round": "ATP Rome - 1/16-finals",
      "event_type": "Atp Singles",
      "qualification": false,
      "tour_level": "atp",
      "gender": "men",
      "odds": 2.07,
      "best_bookmaker": "Pncl",
      "market_median_odds": 1.99,
      "bookmakers_used": 5,
      "model_prob": 0.57,
      "implied_prob": 0.4831,
      "edge": 0.0869,
      "expected_total_games": 19.36,
      "expected_margin": -1.14,
      "confidence": 73.7,
      "quality_score": 68.5,
      "stake": 0.25,
      "stake_label": "Small Value",
      "market_info": {
        "home_median_odds": 3.5,
        "away_median_odds": 1.3,
        "home_implied": 0.2857,
        "away_implied": 0.7692,
        "market_gap": 0.4835,
        "market_favorite_side": "away"
      },
      "first_form": {
        "last_5": {
          "matches": 5,
          "avg_total_games": 24.4,
          "median_total_games": 20,
          "over_21_5_rate": 0.4,
          "over_22_5_rate": 0.4,
          "three_set_rate": 0.6,
          "straight_set_rate": 0.4,
          "close_set_rate": 0.5333,
          "avg_set_diff": 1.0,
          "avg_game_diff": 3.2,
          "win_rate": 1.0
        },
        "last_10": {
          "matches": 9,
          "avg_total_games": 22.22,
          "median_total_games": 20,
          "over_21_5_rate": 0.3333,
          "over_22_5_rate": 0.3333,
          "three_set_rate": 0.4444,
          "straight_set_rate": 0.5556,
          "close_set_rate": 0.4444,
          "avg_set_diff": 0.667,
          "avg_game_diff": 2.0,
          "win_rate": 0.7778
        },
        "last_20": {
          "matches": 9,
          "avg_total_games": 22.22,
          "median_total_games": 20,
          "over_21_5_rate": 0.3333,
          "over_22_5_rate": 0.3333,
          "three_set_rate": 0.4444,
          "straight_set_rate": 0.5556,
          "close_set_rate": 0.4444,
          "avg_set_diff": 0.667,
          "avg_game_diff": 2.0,
          "win_rate": 0.7778
        }
      },
      "second_form": {
        "last_5": {
          "matches": 5,
          "avg_total_games": 24.0,
          "median_total_games": 26,
          "over_21_5_rate": 0.6,
          "over_22_5_rate": 0.6,
          "three_set_rate": 0.6,
          "straight_set_rate": 0.4,
          "close_set_rate": 0.3667,
          "avg_set_diff": 1.0,
          "avg_game_diff": 3.2,
          "win_rate": 0.8
        },
        "last_10": {
          "matches": 8,
          "avg_total_games": 21.25,
          "median_total_games": 18.0,
          "over_21_5_rate": 0.375,
          "over_22_5_rate": 0.375,
          "three_set_rate": 0.375,
          "straight_set_rate": 0.625,
          "close_set_rate": 0.2292,
          "avg_set_diff": 1.375,
          "avg_game_diff": 4.75,
          "win_rate": 0.875
        },
        "last_20": {
          "matches": 8,
          "avg_total_games": 21.25,
          "median_total_games": 18.0,
          "over_21_5_rate": 0.375,
          "over_22_5_rate": 0.375,
          "three_set_rate": 0.375,
          "straight_set_rate": 0.625,
          "close_set_rate": 0.2292,
          "avg_set_diff": 1.375,
          "avg_game_diff": 4.75,
          "win_rate": 0.875
        }
      },
      "first_strength_score": 73.17,
      "second_strength_score": 90.75,
      "h2h_matches": 0,
      "result": "pending",
      "created_at": "2026-05-10T09:24:57.563298+02:00",
      "reasoning": "UNDER 20.5 games selected in M. Arnaldi - R. Jodar at line 20.5. Model expected total games: 19.36; market line: 20.5. Model probability 57.0% versus implied 48.3% from best odds 2.07. Edge: +8.7%. Bookmakers used: 5. Confidence: 73.7."
    }
  ]
}
