{
  "overall": {
    "picks": 354,
    "wins": 160,
    "losses": 194,
    "win_rate": 45.2,
    "staked": 426.75,
    "profit": -6.83,
    "roi": -1.6,
    "avg_odds": 2.251,
    "max_drawdown_units": 18.36,
    "longest_loss_streak": 9
  },
  "single_segments": {
    "by_odds": {
      "1.90-2.09": {
        "picks": 51,
        "wins": 29,
        "losses": 22,
        "win_rate": 56.86,
        "staked": 56.75,
        "profit": 6.21,
        "roi": 10.94,
        "avg_odds": 1.967,
        "max_drawdown_units": 5.31,
        "longest_loss_streak": 4
      },
      "1.70-1.89": {
        "picks": 50,
        "wins": 30,
        "losses": 20,
        "win_rate": 60.0,
        "staked": 51.5,
        "profit": 5.64,
        "roi": 10.95,
        "avg_odds": 1.802,
        "max_drawdown_units": 4.86,
        "longest_loss_streak": 3
      },
      "2.70+": {
        "picks": 32,
        "wins": 12,
        "losses": 20,
        "win_rate": 37.5,
        "staked": 37.25,
        "profit": 0.85,
        "roi": 2.28,
        "avg_odds": 2.783,
        "max_drawdown_units": 7.43,
        "longest_loss_streak": 5
      },
      "<1.70": {
        "picks": 2,
        "wins": 1,
        "losses": 1,
        "win_rate": 50.0,
        "staked": 2.25,
        "profit": -0.98,
        "roi": -43.67,
        "avg_odds": 1.685,
        "max_drawdown_units": 1.5,
        "longest_loss_streak": 1
      },
      "2.40-2.70": {
        "picks": 80,
        "wins": 30,
        "losses": 50,
        "win_rate": 37.5,
        "staked": 96.5,
        "profit": -6.86,
        "roi": -7.11,
        "avg_odds": 2.53,
        "max_drawdown_units": 17.09,
        "longest_loss_streak": 6
      },
      "2.10-2.39": {
        "picks": 139,
        "wins": 58,
        "losses": 81,
        "win_rate": 41.73,
        "staked": 182.5,
        "profit": -11.68,
        "roi": -6.4,
        "avg_odds": 2.242,
        "max_drawdown_units": 22.09,
        "longest_loss_streak": 5
      }
    },
    "by_edge": {
      "6.5-7.9%": {
        "picks": 36,
        "wins": 25,
        "losses": 11,
        "win_rate": 69.44,
        "staked": 30.5,
        "profit": 11.12,
        "roi": 36.48,
        "avg_odds": 1.957,
        "max_drawdown_units": 1.97,
        "longest_loss_streak": 2
      },
      "10-11.9%": {
        "picks": 43,
        "wins": 26,
        "losses": 17,
        "win_rate": 60.47,
        "staked": 47.5,
        "profit": 10.42,
        "roi": 21.94,
        "avg_odds": 2.057,
        "max_drawdown_units": 4.22,
        "longest_loss_streak": 3
      },
      "8-9.9%": {
        "picks": 25,
        "wins": 9,
        "losses": 16,
        "win_rate": 36.0,
        "staked": 24.25,
        "profit": -7.28,
        "roi": -30.03,
        "avg_odds": 1.959,
        "max_drawdown_units": 7.28,
        "longest_loss_streak": 4
      },
      "12%+": {
        "picks": 250,
        "wins": 100,
        "losses": 150,
        "win_rate": 40.0,
        "staked": 324.5,
        "profit": -21.1,
        "roi": -6.5,
        "avg_odds": 2.356,
        "max_drawdown_units": 27.69,
        "longest_loss_streak": 8
      }
    },
    "by_confidence": {
      "82-85.9": {
        "picks": 22,
        "wins": 13,
        "losses": 9,
        "win_rate": 59.09,
        "staked": 24.75,
        "profit": 11.46,
        "roi": 46.32,
        "avg_odds": 2.376,
        "max_drawdown_units": 4.09,
        "longest_loss_streak": 3
      },
      "<74": {
        "picks": 4,
        "wins": 4,
        "losses": 0,
        "win_rate": 100.0,
        "staked": 3.0,
        "profit": 4.23,
        "roi": 141.0,
        "avg_odds": 2.41,
        "max_drawdown_units": 0,
        "longest_loss_streak": 0
      },
      "74-77.9": {
        "picks": 9,
        "wins": 4,
        "losses": 5,
        "win_rate": 44.44,
        "staked": 8.5,
        "profit": 1.55,
        "roi": 18.29,
        "avg_odds": 2.711,
        "max_drawdown_units": 2.75,
        "longest_loss_streak": 3
      },
      "78-81.9": {
        "picks": 9,
        "wins": 4,
        "losses": 5,
        "win_rate": 44.44,
        "staked": 8.0,
        "profit": 0.37,
        "roi": 4.59,
        "avg_odds": 2.544,
        "max_drawdown_units": 3.0,
        "longest_loss_streak": 3
      },
      "86+": {
        "picks": 310,
        "wins": 135,
        "losses": 175,
        "win_rate": 43.55,
        "staked": 382.5,
        "profit": -24.45,
        "roi": -6.39,
        "avg_odds": 2.218,
        "max_drawdown_units": 31.58,
        "longest_loss_streak": 10
      }
    },
    "by_stake_label": {
      "Small Value": {
        "picks": 26,
        "wins": 18,
        "losses": 8,
        "win_rate": 69.23,
        "staked": 19.5,
        "profit": 8.84,
        "roi": 45.31,
        "avg_odds": 2.085,
        "max_drawdown_units": 2.25,
        "longest_loss_streak": 3
      },
      "Strong": {
        "picks": 201,
        "wins": 88,
        "losses": 113,
        "win_rate": 43.78,
        "staked": 251.25,
        "profit": 0.57,
        "roi": 0.23,
        "avg_odds": 2.348,
        "max_drawdown_units": 17.39,
        "longest_loss_streak": 8
      },
      "Standard": {
        "picks": 69,
        "wins": 31,
        "losses": 38,
        "win_rate": 44.93,
        "staked": 69.0,
        "profit": -6.42,
        "roi": -9.3,
        "avg_odds": 2.059,
        "max_drawdown_units": 9.05,
        "longest_loss_streak": 4
      },
      "Top Rated": {
        "picks": 58,
        "wins": 23,
        "losses": 35,
        "win_rate": 39.66,
        "staked": 87.0,
        "profit": -9.82,
        "roi": -11.29,
        "avg_odds": 2.216,
        "max_drawdown_units": 17.61,
        "longest_loss_streak": 6
      }
    },
    "by_tour_level": {
      "challenger": {
        "picks": 116,
        "wins": 60,
        "losses": 56,
        "win_rate": 51.72,
        "staked": 143.5,
        "profit": 18.1,
        "roi": 12.61,
        "avg_odds": 2.228,
        "max_drawdown_units": 7.76,
        "longest_loss_streak": 4
      },
      "itf": {
        "picks": 123,
        "wins": 53,
        "losses": 70,
        "win_rate": 43.09,
        "staked": 140.75,
        "profit": -5.78,
        "roi": -4.1,
        "avg_odds": 2.255,
        "max_drawdown_units": 15.29,
        "longest_loss_streak": 7
      },
      "wta": {
        "picks": 45,
        "wins": 20,
        "losses": 25,
        "win_rate": 44.44,
        "staked": 54.0,
        "profit": -8.8,
        "roi": -16.3,
        "avg_odds": 2.203,
        "max_drawdown_units": 11.27,
        "longest_loss_streak": 5
      },
      "atp": {
        "picks": 70,
        "wins": 27,
        "losses": 43,
        "win_rate": 38.57,
        "staked": 88.5,
        "profit": -10.36,
        "roi": -11.7,
        "avg_odds": 2.312,
        "max_drawdown_units": 15.14,
        "longest_loss_streak": 8
      }
    },
    "by_gender": {
      "unknown": {
        "picks": 7,
        "wins": 4,
        "losses": 3,
        "win_rate": 57.14,
        "staked": 9.0,
        "profit": 2.06,
        "roi": 22.92,
        "avg_odds": 2.243,
        "max_drawdown_units": 2.75,
        "longest_loss_streak": 2
      },
      "men": {
        "picks": 219,
        "wins": 99,
        "losses": 120,
        "win_rate": 45.21,
        "staked": 262.25,
        "profit": -1.51,
        "roi": -0.57,
        "avg_odds": 2.253,
        "max_drawdown_units": 13.74,
        "longest_loss_streak": 8
      },
      "women": {
        "picks": 128,
        "wins": 57,
        "losses": 71,
        "win_rate": 44.53,
        "staked": 155.5,
        "profit": -7.39,
        "roi": -4.75,
        "avg_odds": 2.248,
        "max_drawdown_units": 11.35,
        "longest_loss_streak": 8
      }
    },
    "by_favorite_type": {
      "favorite": {
        "picks": 85,
        "wins": 49,
        "losses": 36,
        "win_rate": 57.65,
        "staked": 91.25,
        "profit": 6.27,
        "roi": 6.87,
        "avg_odds": 1.85,
        "max_drawdown_units": 5.82,
        "longest_loss_streak": 4
      },
      "underdog": {
        "picks": 269,
        "wins": 111,
        "losses": 158,
        "win_rate": 41.26,
        "staked": 335.5,
        "profit": -13.11,
        "roi": -3.91,
        "avg_odds": 2.378,
        "max_drawdown_units": 25.06,
        "longest_loss_streak": 8
      }
    }
  },
  "cross_segments": {
    "odds_x_tour": [
      {
        "picks": 10,
        "wins": 5,
        "losses": 5,
        "win_rate": 50.0,
        "staked": 12.25,
        "profit": 4.42,
        "roi": 36.12,
        "avg_odds": 2.789,
        "max_drawdown_units": 3.75,
        "longest_loss_streak": 3,
        "segment": "2.70+ | challenger"
      },
      {
        "picks": 47,
        "wins": 24,
        "losses": 23,
        "win_rate": 51.06,
        "staked": 62.5,
        "profit": 10.22,
        "roi": 16.36,
        "avg_odds": 2.241,
        "max_drawdown_units": 5.25,
        "longest_loss_streak": 4,
        "segment": "2.10-2.39 | challenger"
      },
      {
        "picks": 16,
        "wins": 10,
        "losses": 6,
        "win_rate": 62.5,
        "staked": 19.5,
        "profit": 3.11,
        "roi": 15.95,
        "avg_odds": 1.977,
        "max_drawdown_units": 3.3,
        "longest_loss_streak": 2,
        "segment": "1.90-2.09 | challenger"
      },
      {
        "picks": 11,
        "wins": 6,
        "losses": 5,
        "win_rate": 54.55,
        "staked": 12.75,
        "profit": 1.35,
        "roi": 10.59,
        "avg_odds": 1.96,
        "max_drawdown_units": 2.32,
        "longest_loss_streak": 2,
        "segment": "1.90-2.09 | atp"
      },
      {
        "picks": 15,
        "wins": 8,
        "losses": 7,
        "win_rate": 53.33,
        "staked": 14.5,
        "profit": 1.33,
        "roi": 9.17,
        "avg_odds": 1.962,
        "max_drawdown_units": 2.66,
        "longest_loss_streak": 2,
        "segment": "1.90-2.09 | itf"
      },
      {
        "picks": 23,
        "wins": 10,
        "losses": 13,
        "win_rate": 43.48,
        "staked": 28.0,
        "profit": 1.44,
        "roi": 5.15,
        "avg_odds": 2.522,
        "max_drawdown_units": 7.48,
        "longest_loss_streak": 5,
        "segment": "2.40-2.70 | challenger"
      },
      {
        "picks": 19,
        "wins": 10,
        "losses": 9,
        "win_rate": 52.63,
        "staked": 18.75,
        "profit": 0.12,
        "roi": 0.64,
        "avg_odds": 1.819,
        "max_drawdown_units": 3.25,
        "longest_loss_streak": 3,
        "segment": "1.70-1.89 | itf"
      },
      {
        "picks": 18,
        "wins": 10,
        "losses": 8,
        "win_rate": 55.56,
        "staked": 19.0,
        "profit": -0.11,
        "roi": -0.61,
        "avg_odds": 1.792,
        "max_drawdown_units": 3.25,
        "longest_loss_streak": 3,
        "segment": "1.70-1.89 | challenger"
      },
      {
        "picks": 26,
        "wins": 10,
        "losses": 16,
        "win_rate": 38.46,
        "staked": 31.0,
        "profit": -1.29,
        "roi": -4.17,
        "avg_odds": 2.526,
        "max_drawdown_units": 10.22,
        "longest_loss_streak": 4,
        "segment": "2.40-2.70 | itf"
      },
      {
        "picks": 14,
        "wins": 5,
        "losses": 9,
        "win_rate": 35.71,
        "staked": 15.25,
        "profit": -0.81,
        "roi": -5.33,
        "avg_odds": 2.767,
        "max_drawdown_units": 5.25,
        "longest_loss_streak": 4,
        "segment": "2.70+ | itf"
      },
      {
        "picks": 49,
        "wins": 20,
        "losses": 29,
        "win_rate": 40.82,
        "staked": 61.25,
        "profit": -5.12,
        "roi": -8.36,
        "avg_odds": 2.224,
        "max_drawdown_units": 8.1,
        "longest_loss_streak": 6,
        "segment": "2.10-2.39 | itf"
      },
      {
        "picks": 21,
        "wins": 7,
        "losses": 14,
        "win_rate": 33.33,
        "staked": 25.25,
        "profit": -2.8,
        "roi": -11.09,
        "avg_odds": 2.546,
        "max_drawdown_units": 6.03,
        "longest_loss_streak": 5,
        "segment": "2.40-2.70 | atp"
      },
      {
        "picks": 28,
        "wins": 10,
        "losses": 18,
        "win_rate": 35.71,
        "staked": 39.25,
        "profit": -6.88,
        "roi": -17.54,
        "avg_odds": 2.283,
        "max_drawdown_units": 11.46,
        "longest_loss_streak": 7,
        "segment": "2.10-2.39 | atp"
      },
      {
        "picks": 10,
        "wins": 3,
        "losses": 7,
        "win_rate": 30.0,
        "staked": 12.25,
        "profit": -4.21,
        "roi": -34.39,
        "avg_odds": 2.523,
        "max_drawdown_units": 4.24,
        "longest_loss_streak": 3,
        "segment": "2.40-2.70 | wta"
      },
      {
        "picks": 15,
        "wins": 4,
        "losses": 11,
        "win_rate": 26.67,
        "staked": 19.5,
        "profit": -9.9,
        "roi": -50.78,
        "avg_odds": 2.228,
        "max_drawdown_units": 11.59,
        "longest_loss_streak": 5,
        "segment": "2.10-2.39 | wta"
      }
    ],
    "odds_x_edge": [
      {
        "picks": 10,
        "wins": 7,
        "losses": 3,
        "win_rate": 70.0,
        "staked": 9.75,
        "profit": 3.72,
        "roi": 38.13,
        "avg_odds": 1.984,
        "max_drawdown_units": 2.0,
        "longest_loss_streak": 2,
        "segment": "1.90-2.09 | 8-9.9%"
      },
      {
        "picks": 21,
        "wins": 15,
        "losses": 6,
        "win_rate": 71.43,
        "staked": 24.25,
        "profit": 7.78,
        "roi": 32.06,
        "avg_odds": 1.828,
        "max_drawdown_units": 3.25,
        "longest_loss_streak": 3,
        "segment": "1.70-1.89 | 10-11.9%"
      },
      {
        "picks": 16,
        "wins": 11,
        "losses": 5,
        "win_rate": 68.75,
        "staked": 13.75,
        "profit": 3.19,
        "roi": 23.18,
        "avg_odds": 1.783,
        "max_drawdown_units": 1.5,
        "longest_loss_streak": 2,
        "segment": "1.70-1.89 | 6.5-7.9%"
      },
      {
        "picks": 19,
        "wins": 11,
        "losses": 8,
        "win_rate": 57.89,
        "staked": 25.75,
        "profit": 3.1,
        "roi": 12.06,
        "avg_odds": 1.954,
        "max_drawdown_units": 4.29,
        "longest_loss_streak": 3,
        "segment": "1.90-2.09 | 12%+"
      },
      {
        "picks": 13,
        "wins": 7,
        "losses": 6,
        "win_rate": 53.85,
        "staked": 11.5,
        "profit": 0.58,
        "roi": 5.04,
        "avg_odds": 1.932,
        "max_drawdown_units": 2.54,
        "longest_loss_streak": 2,
        "segment": "1.90-2.09 | 6.5-7.9%"
      },
      {
        "picks": 27,
        "wins": 9,
        "losses": 18,
        "win_rate": 33.33,
        "staked": 32.75,
        "profit": -2.26,
        "roi": -6.91,
        "avg_odds": 2.785,
        "max_drawdown_units": 7.68,
        "longest_loss_streak": 5,
        "segment": "2.70+ | 12%+"
      },
      {
        "picks": 129,
        "wins": 53,
        "losses": 76,
        "win_rate": 41.09,
        "staked": 172.25,
        "profit": -12.22,
        "roi": -7.09,
        "avg_odds": 2.242,
        "max_drawdown_units": 22.04,
        "longest_loss_streak": 5,
        "segment": "2.10-2.39 | 12%+"
      },
      {
        "picks": 72,
        "wins": 25,
        "losses": 47,
        "win_rate": 34.72,
        "staked": 89.75,
        "profit": -10.4,
        "roi": -11.59,
        "avg_odds": 2.528,
        "max_drawdown_units": 19.6,
        "longest_loss_streak": 6,
        "segment": "2.40-2.70 | 12%+"
      },
      {
        "picks": 11,
        "wins": 2,
        "losses": 9,
        "win_rate": 18.18,
        "staked": 11.0,
        "profit": -7.5,
        "roi": -68.18,
        "avg_odds": 1.767,
        "max_drawdown_units": 7.5,
        "longest_loss_streak": 5,
        "segment": "1.70-1.89 | 8-9.9%"
      }
    ],
    "odds_x_confidence": [
      {
        "picks": 46,
        "wins": 27,
        "losses": 19,
        "win_rate": 58.7,
        "staked": 52.75,
        "profit": 7.25,
        "roi": 13.75,
        "avg_odds": 1.967,
        "max_drawdown_units": 5.25,
        "longest_loss_streak": 4,
        "segment": "1.90-2.09 | 86+"
      },
      {
        "picks": 49,
        "wins": 29,
        "losses": 20,
        "win_rate": 59.18,
        "staked": 50.75,
        "profit": 4.97,
        "roi": 9.79,
        "avg_odds": 1.8,
        "max_drawdown_units": 4.86,
        "longest_loss_streak": 3,
        "segment": "1.70-1.89 | 86+"
      },
      {
        "picks": 20,
        "wins": 7,
        "losses": 13,
        "win_rate": 35.0,
        "staked": 25.0,
        "profit": -0.73,
        "roi": -2.9,
        "avg_odds": 2.784,
        "max_drawdown_units": 8.12,
        "longest_loss_streak": 5,
        "segment": "2.70+ | 86+"
      },
      {
        "picks": 131,
        "wins": 52,
        "losses": 79,
        "win_rate": 39.69,
        "staked": 174.25,
        "profit": -17.97,
        "roi": -10.31,
        "avg_odds": 2.239,
        "max_drawdown_units": 26.08,
        "longest_loss_streak": 5,
        "segment": "2.10-2.39 | 86+"
      },
      {
        "picks": 62,
        "wins": 19,
        "losses": 43,
        "win_rate": 30.65,
        "staked": 77.5,
        "profit": -17.0,
        "roi": -21.94,
        "avg_odds": 2.527,
        "max_drawdown_units": 21.62,
        "longest_loss_streak": 8,
        "segment": "2.40-2.70 | 86+"
      }
    ],
    "odds_x_favorite": [
      {
        "picks": 18,
        "wins": 11,
        "losses": 7,
        "win_rate": 61.11,
        "staked": 19.25,
        "profit": 4.59,
        "roi": 23.84,
        "avg_odds": 2.031,
        "max_drawdown_units": 2.5,
        "longest_loss_streak": 2,
        "segment": "1.90-2.09 | underdog"
      },
      {
        "picks": 50,
        "wins": 30,
        "losses": 20,
        "win_rate": 60.0,
        "staked": 51.5,
        "profit": 5.64,
        "roi": 10.95,
        "avg_odds": 1.802,
        "max_drawdown_units": 4.86,
        "longest_loss_streak": 3,
        "segment": "1.70-1.89 | favorite"
      },
      {
        "picks": 33,
        "wins": 18,
        "losses": 15,
        "win_rate": 54.55,
        "staked": 37.5,
        "profit": 1.62,
        "roi": 4.31,
        "avg_odds": 1.932,
        "max_drawdown_units": 5.43,
        "longest_loss_streak": 4,
        "segment": "1.90-2.09 | favorite"
      },
      {
        "picks": 32,
        "wins": 12,
        "losses": 20,
        "win_rate": 37.5,
        "staked": 37.25,
        "profit": 0.85,
        "roi": 2.28,
        "avg_odds": 2.783,
        "max_drawdown_units": 7.43,
        "longest_loss_streak": 5,
        "segment": "2.70+ | underdog"
      },
      {
        "picks": 139,
        "wins": 58,
        "losses": 81,
        "win_rate": 41.73,
        "staked": 182.5,
        "profit": -11.68,
        "roi": -6.4,
        "avg_odds": 2.242,
        "max_drawdown_units": 22.09,
        "longest_loss_streak": 5,
        "segment": "2.10-2.39 | underdog"
      },
      {
        "picks": 80,
        "wins": 30,
        "losses": 50,
        "win_rate": 37.5,
        "staked": 96.5,
        "profit": -6.86,
        "roi": -7.11,
        "avg_odds": 2.53,
        "max_drawdown_units": 17.09,
        "longest_loss_streak": 6,
        "segment": "2.40-2.70 | underdog"
      }
    ],
    "tour_x_favorite": [
      {
        "picks": 13,
        "wins": 9,
        "losses": 4,
        "win_rate": 69.23,
        "staked": 14.5,
        "profit": 3.48,
        "roi": 24.0,
        "avg_odds": 1.854,
        "max_drawdown_units": 2.84,
        "longest_loss_streak": 2,
        "segment": "wta | favorite"
      },
      {
        "picks": 14,
        "wins": 9,
        "losses": 5,
        "win_rate": 64.29,
        "staked": 16.25,
        "profit": 3.55,
        "roi": 21.85,
        "avg_odds": 1.877,
        "max_drawdown_units": 2.5,
        "longest_loss_streak": 2,
        "segment": "atp | favorite"
      },
      {
        "picks": 88,
        "wins": 44,
        "losses": 44,
        "win_rate": 50.0,
        "staked": 112.0,
        "profit": 17.96,
        "roi": 16.03,
        "avg_odds": 2.357,
        "max_drawdown_units": 7.53,
        "longest_loss_streak": 4,
        "segment": "challenger | underdog"
      },
      {
        "picks": 28,
        "wins": 16,
        "losses": 12,
        "win_rate": 57.14,
        "staked": 31.5,
        "profit": 0.15,
        "roi": 0.46,
        "avg_odds": 1.821,
        "max_drawdown_units": 5.5,
        "longest_loss_streak": 4,
        "segment": "challenger | favorite"
      },
      {
        "picks": 30,
        "wins": 15,
        "losses": 15,
        "win_rate": 50.0,
        "staked": 29.0,
        "profit": -0.9,
        "roi": -3.11,
        "avg_odds": 1.861,
        "max_drawdown_units": 5.89,
        "longest_loss_streak": 4,
        "segment": "itf | favorite"
      },
      {
        "picks": 93,
        "wins": 38,
        "losses": 55,
        "win_rate": 40.86,
        "staked": 111.75,
        "profit": -4.88,
        "roi": -4.36,
        "avg_odds": 2.382,
        "max_drawdown_units": 13.45,
        "longest_loss_streak": 6,
        "segment": "itf | underdog"
      },
      {
        "picks": 56,
        "wins": 18,
        "losses": 38,
        "win_rate": 32.14,
        "staked": 72.25,
        "profit": -13.91,
        "roi": -19.25,
        "avg_odds": 2.421,
        "max_drawdown_units": 19.53,
        "longest_loss_streak": 9,
        "segment": "atp | underdog"
      },
      {
        "picks": 32,
        "wins": 11,
        "losses": 21,
        "win_rate": 34.38,
        "staked": 39.5,
        "profit": -12.28,
        "roi": -31.09,
        "avg_odds": 2.345,
        "max_drawdown_units": 13.97,
        "longest_loss_streak": 6,
        "segment": "wta | underdog"
      }
    ],
    "stake_x_odds": [
      {
        "picks": 15,
        "wins": 12,
        "losses": 3,
        "win_rate": 80.0,
        "staked": 18.75,
        "profit": 8.85,
        "roi": 47.2,
        "avg_odds": 1.837,
        "max_drawdown_units": 1.44,
        "longest_loss_streak": 1,
        "segment": "Strong | 1.70-1.89"
      },
      {
        "picks": 22,
        "wins": 13,
        "losses": 9,
        "win_rate": 59.09,
        "staked": 22.0,
        "profit": 3.75,
        "roi": 17.05,
        "avg_odds": 1.974,
        "max_drawdown_units": 2.1,
        "longest_loss_streak": 2,
        "segment": "Standard | 1.90-2.09"
      },
      {
        "picks": 14,
        "wins": 8,
        "losses": 6,
        "win_rate": 57.14,
        "staked": 17.5,
        "profit": 2.22,
        "roi": 12.71,
        "avg_odds": 1.977,
        "max_drawdown_units": 3.69,
        "longest_loss_streak": 2,
        "segment": "Strong | 1.90-2.09"
      },
      {
        "picks": 82,
        "wins": 36,
        "losses": 46,
        "win_rate": 43.9,
        "staked": 102.5,
        "profit": -1.49,
        "roi": -1.45,
        "avg_odds": 2.231,
        "max_drawdown_units": 15.24,
        "longest_loss_streak": 5,
        "segment": "Strong | 2.10-2.39"
      },
      {
        "picks": 23,
        "wins": 8,
        "losses": 15,
        "win_rate": 34.78,
        "staked": 28.75,
        "profit": -1.01,
        "roi": -3.52,
        "avg_odds": 2.784,
        "max_drawdown_units": 8.41,
        "longest_loss_streak": 6,
        "segment": "Strong | 2.70+"
      },
      {
        "picks": 67,
        "wins": 24,
        "losses": 43,
        "win_rate": 35.82,
        "staked": 83.75,
        "profit": -8.0,
        "roi": -9.55,
        "avg_odds": 2.534,
        "max_drawdown_units": 17.6,
        "longest_loss_streak": 5,
        "segment": "Strong | 2.40-2.70"
      },
      {
        "picks": 47,
        "wins": 18,
        "losses": 29,
        "win_rate": 38.3,
        "staked": 70.5,
        "profit": -8.58,
        "roi": -12.17,
        "avg_odds": 2.266,
        "max_drawdown_units": 16.36,
        "longest_loss_streak": 9,
        "segment": "Top Rated | 2.10-2.39"
      },
      {
        "picks": 26,
        "wins": 12,
        "losses": 14,
        "win_rate": 46.15,
        "staked": 26.0,
        "profit": -4.51,
        "roi": -17.35,
        "avg_odds": 1.788,
        "max_drawdown_units": 6.79,
        "longest_loss_streak": 5,
        "segment": "Standard | 1.70-1.89"
      }
    ],
    "confidence_x_edge": [
      {
        "picks": 14,
        "wins": 9,
        "losses": 5,
        "win_rate": 64.29,
        "staked": 17.5,
        "profit": 10.76,
        "roi": 61.5,
        "avg_odds": 2.566,
        "max_drawdown_units": 2.5,
        "longest_loss_streak": 2,
        "segment": "82-85.9 | 12%+"
      },
      {
        "picks": 25,
        "wins": 16,
        "losses": 9,
        "win_rate": 64.0,
        "staked": 22.25,
        "profit": 3.66,
        "roi": 16.46,
        "avg_odds": 1.822,
        "max_drawdown_units": 2.5,
        "longest_loss_streak": 3,
        "segment": "86+ | 6.5-7.9%"
      },
      {
        "picks": 34,
        "wins": 20,
        "losses": 14,
        "win_rate": 58.82,
        "staked": 38.5,
        "profit": 4.28,
        "roi": 11.12,
        "avg_odds": 1.925,
        "max_drawdown_units": 3.45,
        "longest_loss_streak": 3,
        "segment": "86+ | 10-11.9%"
      },
      {
        "picks": 231,
        "wins": 90,
        "losses": 141,
        "win_rate": 38.96,
        "staked": 302.0,
        "profit": -29.61,
        "roi": -9.81,
        "avg_odds": 2.335,
        "max_drawdown_units": 36.2,
        "longest_loss_streak": 8,
        "segment": "86+ | 12%+"
      },
      {
        "picks": 20,
        "wins": 9,
        "losses": 11,
        "win_rate": 45.0,
        "staked": 19.75,
        "profit": -2.78,
        "roi": -14.09,
        "avg_odds": 1.865,
        "max_drawdown_units": 4.41,
        "longest_loss_streak": 4,
        "segment": "86+ | 8-9.9%"
      }
    ]
  },
  "multi_segments": {
    "tour_x_favorite_x_odds": [
      {
        "picks": 8,
        "wins": 7,
        "losses": 1,
        "win_rate": 87.5,
        "staked": 8.5,
        "profit": 5.18,
        "roi": 60.97,
        "avg_odds": 1.815,
        "max_drawdown_units": 1.0,
        "longest_loss_streak": 1,
        "segment": "wta | favorite | 1.70-1.89"
      },
      {
        "picks": 10,
        "wins": 5,
        "losses": 5,
        "win_rate": 50.0,
        "staked": 12.25,
        "profit": 4.42,
        "roi": 36.12,
        "avg_odds": 2.789,
        "max_drawdown_units": 3.75,
        "longest_loss_streak": 3,
        "segment": "challenger | underdog | 2.70+"
      },
      {
        "picks": 9,
        "wins": 6,
        "losses": 3,
        "win_rate": 66.67,
        "staked": 11.0,
        "profit": 3.1,
        "roi": 28.18,
        "avg_odds": 1.948,
        "max_drawdown_units": 1.5,
        "longest_loss_streak": 1,
        "segment": "atp | favorite | 1.90-2.09"
      },
      {
        "picks": 8,
        "wins": 5,
        "losses": 3,
        "win_rate": 62.5,
        "staked": 9.25,
        "profit": 1.87,
        "roi": 20.19,
        "avg_odds": 2.032,
        "max_drawdown_units": 2.5,
        "longest_loss_streak": 2,
        "segment": "challenger | underdog | 1.90-2.09"
      },
      {
        "picks": 47,
        "wins": 24,
        "losses": 23,
        "win_rate": 51.06,
        "staked": 62.5,
        "profit": 10.22,
        "roi": 16.36,
        "avg_odds": 2.241,
        "max_drawdown_units": 5.25,
        "longest_loss_streak": 4,
        "segment": "challenger | underdog | 2.10-2.39"
      },
      {
        "picks": 8,
        "wins": 5,
        "losses": 3,
        "win_rate": 62.5,
        "staked": 10.25,
        "profit": 1.24,
        "roi": 12.12,
        "avg_odds": 1.921,
        "max_drawdown_units": 2.75,
        "longest_loss_streak": 2,
        "segment": "challenger | favorite | 1.90-2.09"
      },
      {
        "picks": 23,
        "wins": 10,
        "losses": 13,
        "win_rate": 43.48,
        "staked": 28.0,
        "profit": 1.44,
        "roi": 5.15,
        "avg_odds": 2.522,
        "max_drawdown_units": 7.48,
        "longest_loss_streak": 5,
        "segment": "challenger | underdog | 2.40-2.70"
      },
      {
        "picks": 19,
        "wins": 10,
        "losses": 9,
        "win_rate": 52.63,
        "staked": 18.75,
        "profit": 0.12,
        "roi": 0.64,
        "avg_odds": 1.819,
        "max_drawdown_units": 3.25,
        "longest_loss_streak": 3,
        "segment": "itf | favorite | 1.70-1.89"
      },
      {
        "picks": 18,
        "wins": 10,
        "losses": 8,
        "win_rate": 55.56,
        "staked": 19.0,
        "profit": -0.11,
        "roi": -0.61,
        "avg_odds": 1.792,
        "max_drawdown_units": 3.25,
        "longest_loss_streak": 3,
        "segment": "challenger | favorite | 1.70-1.89"
      },
      {
        "picks": 26,
        "wins": 10,
        "losses": 16,
        "win_rate": 38.46,
        "staked": 31.0,
        "profit": -1.29,
        "roi": -4.17,
        "avg_odds": 2.526,
        "max_drawdown_units": 10.22,
        "longest_loss_streak": 4,
        "segment": "itf | underdog | 2.40-2.70"
      },
      {
        "picks": 14,
        "wins": 5,
        "losses": 9,
        "win_rate": 35.71,
        "staked": 15.25,
        "profit": -0.81,
        "roi": -5.33,
        "avg_odds": 2.767,
        "max_drawdown_units": 5.25,
        "longest_loss_streak": 4,
        "segment": "itf | underdog | 2.70+"
      },
      {
        "picks": 49,
        "wins": 20,
        "losses": 29,
        "win_rate": 40.82,
        "staked": 61.25,
        "profit": -5.12,
        "roi": -8.36,
        "avg_odds": 2.224,
        "max_drawdown_units": 8.1,
        "longest_loss_streak": 6,
        "segment": "itf | underdog | 2.10-2.39"
      },
      {
        "picks": 11,
        "wins": 5,
        "losses": 6,
        "win_rate": 45.45,
        "staked": 10.25,
        "profit": -1.02,
        "roi": -9.98,
        "avg_odds": 1.935,
        "max_drawdown_units": 3.83,
        "longest_loss_streak": 4,
        "segment": "itf | favorite | 1.90-2.09"
      },
      {
        "picks": 21,
        "wins": 7,
        "losses": 14,
        "win_rate": 33.33,
        "staked": 25.25,
        "profit": -2.8,
        "roi": -11.09,
        "avg_odds": 2.546,
        "max_drawdown_units": 6.03,
        "longest_loss_streak": 5,
        "segment": "atp | underdog | 2.40-2.70"
      },
      {
        "picks": 28,
        "wins": 10,
        "losses": 18,
        "win_rate": 35.71,
        "staked": 39.25,
        "profit": -6.88,
        "roi": -17.54,
        "avg_odds": 2.283,
        "max_drawdown_units": 11.46,
        "longest_loss_streak": 7,
        "segment": "atp | underdog | 2.10-2.39"
      },
      {
        "picks": 10,
        "wins": 3,
        "losses": 7,
        "win_rate": 30.0,
        "staked": 12.25,
        "profit": -4.21,
        "roi": -34.39,
        "avg_odds": 2.523,
        "max_drawdown_units": 4.24,
        "longest_loss_streak": 3,
        "segment": "wta | underdog | 2.40-2.70"
      },
      {
        "picks": 15,
        "wins": 4,
        "losses": 11,
        "win_rate": 26.67,
        "staked": 19.5,
        "profit": -9.9,
        "roi": -50.78,
        "avg_odds": 2.228,
        "max_drawdown_units": 11.59,
        "longest_loss_streak": 5,
        "segment": "wta | underdog | 2.10-2.39"
      }
    ],
    "tour_x_odds_x_edge": [
      {
        "picks": 9,
        "wins": 4,
        "losses": 5,
        "win_rate": 44.44,
        "staked": 11.25,
        "profit": 2.62,
        "roi": 23.33,
        "avg_odds": 2.788,
        "max_drawdown_units": 3.75,
        "longest_loss_streak": 3,
        "segment": "challenger | 2.70+ | 12%+"
      },
      {
        "picks": 45,
        "wins": 24,
        "losses": 21,
        "win_rate": 53.33,
        "staked": 60.25,
        "profit": 12.47,
        "roi": 20.7,
        "avg_odds": 2.244,
        "max_drawdown_units": 4.34,
        "longest_loss_streak": 3,
        "segment": "challenger | 2.10-2.39 | 12%+"
      },
      {
        "picks": 8,
        "wins": 5,
        "losses": 3,
        "win_rate": 62.5,
        "staked": 8.5,
        "profit": 1.62,
        "roi": 19.0,
        "avg_odds": 1.833,
        "max_drawdown_units": 2.0,
        "longest_loss_streak": 2,
        "segment": "itf | 1.70-1.89 | 10-11.9%"
      },
      {
        "picks": 8,
        "wins": 5,
        "losses": 3,
        "win_rate": 62.5,
        "staked": 9.75,
        "profit": 1.25,
        "roi": 12.77,
        "avg_odds": 1.83,
        "max_drawdown_units": 2.5,
        "longest_loss_streak": 2,
        "segment": "challenger | 1.70-1.89 | 10-11.9%"
      },
      {
        "picks": 9,
        "wins": 5,
        "losses": 4,
        "win_rate": 55.56,
        "staked": 12.25,
        "profit": 0.95,
        "roi": 7.73,
        "avg_odds": 1.959,
        "max_drawdown_units": 2.79,
        "longest_loss_streak": 2,
        "segment": "challenger | 1.90-2.09 | 12%+"
      },
      {
        "picks": 18,
        "wins": 7,
        "losses": 11,
        "win_rate": 38.89,
        "staked": 22.5,
        "profit": -0.05,
        "roi": -0.22,
        "avg_odds": 2.552,
        "max_drawdown_units": 5.0,
        "longest_loss_streak": 4,
        "segment": "atp | 2.40-2.70 | 12%+"
      },
      {
        "picks": 21,
        "wins": 8,
        "losses": 13,
        "win_rate": 38.1,
        "staked": 26.5,
        "profit": -0.84,
        "roi": -3.16,
        "avg_odds": 2.522,
        "max_drawdown_units": 8.64,
        "longest_loss_streak": 6,
        "segment": "challenger | 2.40-2.70 | 12%+"
      },
      {
        "picks": 46,
        "wins": 18,
        "losses": 28,
        "win_rate": 39.13,
        "staked": 58.25,
        "profit": -6.02,
        "roi": -10.33,
        "avg_odds": 2.223,
        "max_drawdown_units": 8.26,
        "longest_loss_streak": 6,
        "segment": "itf | 2.10-2.39 | 12%+"
      },
      {
        "picks": 24,
        "wins": 8,
        "losses": 16,
        "win_rate": 33.33,
        "staked": 29.25,
        "profit": -4.03,
        "roi": -13.76,
        "avg_odds": 2.524,
        "max_drawdown_units": 11.85,
        "longest_loss_streak": 7,
        "segment": "itf | 2.40-2.70 | 12%+"
      },
      {
        "picks": 10,
        "wins": 3,
        "losses": 7,
        "win_rate": 30.0,
        "staked": 11.75,
        "profit": -2.12,
        "roi": -18.09,
        "avg_odds": 2.769,
        "max_drawdown_units": 4.31,
        "longest_loss_streak": 3,
        "segment": "itf | 2.70+ | 12%+"
      },
      {
        "picks": 26,
        "wins": 9,
        "losses": 17,
        "win_rate": 34.62,
        "staked": 37.0,
        "profit": -7.53,
        "roi": -20.36,
        "avg_odds": 2.279,
        "max_drawdown_units": 11.49,
        "longest_loss_streak": 7,
        "segment": "atp | 2.10-2.39 | 12%+"
      },
      {
        "picks": 9,
        "wins": 2,
        "losses": 7,
        "win_rate": 22.22,
        "staked": 11.5,
        "profit": -5.49,
        "roi": -47.72,
        "avg_odds": 2.503,
        "max_drawdown_units": 5.49,
        "longest_loss_streak": 3,
        "segment": "wta | 2.40-2.70 | 12%+"
      },
      {
        "picks": 12,
        "wins": 2,
        "losses": 10,
        "win_rate": 16.67,
        "staked": 16.75,
        "profit": -11.14,
        "roi": -66.49,
        "avg_odds": 2.226,
        "max_drawdown_units": 12.82,
        "longest_loss_streak": 6,
        "segment": "wta | 2.10-2.39 | 12%+"
      }
    ],
    "tour_x_odds_x_stake": [
      {
        "picks": 9,
        "wins": 4,
        "losses": 5,
        "win_rate": 44.44,
        "staked": 11.25,
        "profit": 2.62,
        "roi": 23.33,
        "avg_odds": 2.788,
        "max_drawdown_units": 3.75,
        "longest_loss_streak": 3,
        "segment": "challenger | 2.70+ | Strong"
      },
      {
        "picks": 17,
        "wins": 9,
        "losses": 8,
        "win_rate": 52.94,
        "staked": 25.5,
        "profit": 5.16,
        "roi": 20.24,
        "avg_odds": 2.262,
        "max_drawdown_units": 4.5,
        "longest_loss_streak": 3,
        "segment": "challenger | 2.10-2.39 | Top Rated"
      },
      {
        "picks": 28,
        "wins": 15,
        "losses": 13,
        "win_rate": 53.57,
        "staked": 35.0,
        "profit": 7.06,
        "roi": 20.18,
        "avg_odds": 2.238,
        "max_drawdown_units": 5.0,
        "longest_loss_streak": 4,
        "segment": "challenger | 2.10-2.39 | Strong"
      },
      {
        "picks": 9,
        "wins": 4,
        "losses": 5,
        "win_rate": 44.44,
        "staked": 11.25,
        "profit": 0.24,
        "roi": 2.11,
        "avg_odds": 2.262,
        "max_drawdown_units": 2.5,
        "longest_loss_streak": 2,
        "segment": "atp | 2.10-2.39 | Strong"
      },
      {
        "picks": 18,
        "wins": 7,
        "losses": 11,
        "win_rate": 38.89,
        "staked": 22.5,
        "profit": -0.05,
        "roi": -0.22,
        "avg_odds": 2.552,
        "max_drawdown_units": 5.0,
        "longest_loss_streak": 4,
        "segment": "atp | 2.40-2.70 | Strong"
      },
      {
        "picks": 8,
        "wins": 4,
        "losses": 4,
        "win_rate": 50.0,
        "staked": 10.0,
        "profit": -0.04,
        "roi": -0.38,
        "avg_odds": 2.006,
        "max_drawdown_units": 3.69,
        "longest_loss_streak": 2,
        "segment": "challenger | 1.90-2.09 | Strong"
      },
      {
        "picks": 21,
        "wins": 8,
        "losses": 13,
        "win_rate": 38.1,
        "staked": 26.25,
        "profit": -1.03,
        "roi": -3.9,
        "avg_odds": 2.53,
        "max_drawdown_units": 9.85,
        "longest_loss_streak": 5,
        "segment": "itf | 2.40-2.70 | Strong"
      },
      {
        "picks": 8,
        "wins": 4,
        "losses": 4,
        "win_rate": 50.0,
        "staked": 8.0,
        "profit": -0.84,
        "roi": -10.5,
        "avg_odds": 1.791,
        "max_drawdown_units": 2.5,
        "longest_loss_streak": 2,
        "segment": "challenger | 1.70-1.89 | Standard"
      },
      {
        "picks": 9,
        "wins": 4,
        "losses": 5,
        "win_rate": 44.44,
        "staked": 9.0,
        "profit": -1.02,
        "roi": -11.33,
        "avg_odds": 1.973,
        "max_drawdown_units": 2.0,
        "longest_loss_streak": 2,
        "segment": "itf | 1.90-2.09 | Standard"
      },
      {
        "picks": 20,
        "wins": 7,
        "losses": 13,
        "win_rate": 35.0,
        "staked": 25.0,
        "profit": -2.94,
        "roi": -11.75,
        "avg_odds": 2.528,
        "max_drawdown_units": 8.64,
        "longest_loss_streak": 6,
        "segment": "challenger | 2.40-2.70 | Strong"
      },
      {
        "picks": 40,
        "wins": 15,
        "losses": 25,
        "win_rate": 37.5,
        "staked": 50.0,
        "profit": -8.15,
        "roi": -16.3,
        "avg_odds": 2.22,
        "max_drawdown_units": 8.73,
        "longest_loss_streak": 5,
        "segment": "itf | 2.10-2.39 | Strong"
      },
      {
        "picks": 18,
        "wins": 6,
        "losses": 12,
        "win_rate": 33.33,
        "staked": 27.0,
        "profit": -6.12,
        "roi": -22.67,
        "avg_odds": 2.29,
        "max_drawdown_units": 10.08,
        "longest_loss_streak": 6,
        "segment": "atp | 2.10-2.39 | Top Rated"
      },
      {
        "picks": 8,
        "wins": 2,
        "losses": 6,
        "win_rate": 25.0,
        "staked": 10.0,
        "profit": -3.99,
        "roi": -39.88,
        "avg_odds": 2.516,
        "max_drawdown_units": 3.99,
        "longest_loss_streak": 3,
        "segment": "wta | 2.40-2.70 | Strong"
      },
      {
        "picks": 10,
        "wins": 3,
        "losses": 7,
        "win_rate": 30.0,
        "staked": 10.0,
        "profit": -4.51,
        "roi": -45.1,
        "avg_odds": 1.808,
        "max_drawdown_units": 5.34,
        "longest_loss_streak": 5,
        "segment": "itf | 1.70-1.89 | Standard"
      }
    ],
    "favorite_x_odds_x_edge": [
      {
        "picks": 21,
        "wins": 15,
        "losses": 6,
        "win_rate": 71.43,
        "staked": 24.25,
        "profit": 7.78,
        "roi": 32.06,
        "avg_odds": 1.828,
        "max_drawdown_units": 3.25,
        "longest_loss_streak": 3,
        "segment": "favorite | 1.70-1.89 | 10-11.9%"
      },
      {
        "picks": 16,
        "wins": 11,
        "losses": 5,
        "win_rate": 68.75,
        "staked": 13.75,
        "profit": 3.19,
        "roi": 23.18,
        "avg_odds": 1.783,
        "max_drawdown_units": 1.5,
        "longest_loss_streak": 2,
        "segment": "favorite | 1.70-1.89 | 6.5-7.9%"
      },
      {
        "picks": 11,
        "wins": 6,
        "losses": 5,
        "win_rate": 54.55,
        "staked": 10.0,
        "profit": 0.55,
        "roi": 5.5,
        "avg_odds": 1.916,
        "max_drawdown_units": 1.79,
        "longest_loss_streak": 2,
        "segment": "favorite | 1.90-2.09 | 6.5-7.9%"
      },
      {
        "picks": 15,
        "wins": 8,
        "losses": 7,
        "win_rate": 53.33,
        "staked": 20.75,
        "profit": 0.53,
        "roi": 2.55,
        "avg_odds": 1.935,
        "max_drawdown_units": 4.84,
        "longest_loss_streak": 3,
        "segment": "favorite | 1.90-2.09 | 12%+"
      },
      {
        "picks": 27,
        "wins": 9,
        "losses": 18,
        "win_rate": 33.33,
        "staked": 32.75,
        "profit": -2.26,
        "roi": -6.91,
        "avg_odds": 2.785,
        "max_drawdown_units": 7.68,
        "longest_loss_streak": 5,
        "segment": "underdog | 2.70+ | 12%+"
      },
      {
        "picks": 129,
        "wins": 53,
        "losses": 76,
        "win_rate": 41.09,
        "staked": 172.25,
        "profit": -12.22,
        "roi": -7.09,
        "avg_odds": 2.242,
        "max_drawdown_units": 22.04,
        "longest_loss_streak": 5,
        "segment": "underdog | 2.10-2.39 | 12%+"
      },
      {
        "picks": 72,
        "wins": 25,
        "losses": 47,
        "win_rate": 34.72,
        "staked": 89.75,
        "profit": -10.4,
        "roi": -11.59,
        "avg_odds": 2.528,
        "max_drawdown_units": 19.6,
        "longest_loss_streak": 6,
        "segment": "underdog | 2.40-2.70 | 12%+"
      },
      {
        "picks": 9,
        "wins": 4,
        "losses": 5,
        "win_rate": 44.44,
        "staked": 9.75,
        "profit": -1.2,
        "roi": -12.26,
        "avg_odds": 2.026,
        "max_drawdown_units": 3.0,
        "longest_loss_streak": 3,
        "segment": "underdog | 1.90-2.09 | 10-11.9%"
      },
      {
        "picks": 11,
        "wins": 2,
        "losses": 9,
        "win_rate": 18.18,
        "staked": 11.0,
        "profit": -7.5,
        "roi": -68.18,
        "avg_odds": 1.767,
        "max_drawdown_units": 7.5,
        "longest_loss_streak": 5,
        "segment": "favorite | 1.70-1.89 | 8-9.9%"
      }
    ],
    "tour_x_favorite_x_edge": [
      {
        "picks": 8,
        "wins": 5,
        "losses": 3,
        "win_rate": 62.5,
        "staked": 8.0,
        "profit": 3.44,
        "roi": 43.03,
        "avg_odds": 2.395,
        "max_drawdown_units": 2.25,
        "longest_loss_streak": 2,
        "segment": "itf | underdog | 10-11.9%"
      },
      {
        "picks": 8,
        "wins": 5,
        "losses": 3,
        "win_rate": 62.5,
        "staked": 8.5,
        "profit": 1.62,
        "roi": 19.0,
        "avg_odds": 1.833,
        "max_drawdown_units": 2.0,
        "longest_loss_streak": 2,
        "segment": "itf | favorite | 10-11.9%"
      },
      {
        "picks": 78,
        "wins": 38,
        "losses": 40,
        "win_rate": 48.72,
        "staked": 101.75,
        "profit": 15.57,
        "roi": 15.3,
        "avg_odds": 2.373,
        "max_drawdown_units": 5.63,
        "longest_loss_streak": 4,
        "segment": "challenger | underdog | 12%+"
      },
      {
        "picks": 8,
        "wins": 5,
        "losses": 3,
        "win_rate": 62.5,
        "staked": 9.75,
        "profit": 1.25,
        "roi": 12.77,
        "avg_odds": 1.83,
        "max_drawdown_units": 2.5,
        "longest_loss_streak": 2,
        "segment": "challenger | favorite | 10-11.9%"
      },
      {
        "picks": 81,
        "wins": 30,
        "losses": 51,
        "win_rate": 37.04,
        "staked": 100.5,
        "profit": -10.91,
        "roi": -10.85,
        "avg_odds": 2.377,
        "max_drawdown_units": 17.11,
        "longest_loss_streak": 6,
        "segment": "itf | underdog | 12%+"
      },
      {
        "picks": 49,
        "wins": 17,
        "losses": 32,
        "win_rate": 34.69,
        "staked": 65.5,
        "profit": -10.06,
        "roi": -15.35,
        "avg_odds": 2.436,
        "max_drawdown_units": 16.78,
        "longest_loss_streak": 8,
        "segment": "atp | underdog | 12%+"
      },
      {
        "picks": 13,
        "wins": 6,
        "losses": 7,
        "win_rate": 46.15,
        "staked": 10.75,
        "profit": -1.9,
        "roi": -17.67,
        "avg_odds": 1.858,
        "max_drawdown_units": 4.25,
        "longest_loss_streak": 5,
        "segment": "itf | favorite | 6.5-7.9%"
      },
      {
        "picks": 24,
        "wins": 5,
        "losses": 19,
        "win_rate": 20.83,
        "staked": 32.0,
        "profit": -16.91,
        "roi": -52.85,
        "avg_odds": 2.397,
        "max_drawdown_units": 18.6,
        "longest_loss_streak": 6,
        "segment": "wta | underdog | 12%+"
      }
    ]
  },
  "what_if": [
    {
      "picks": 104,
      "wins": 60,
      "losses": 44,
      "win_rate": 57.69,
      "staked": 102.25,
      "profit": 14.27,
      "roi": 13.95,
      "avg_odds": 1.999,
      "max_drawdown_units": 4.92,
      "longest_loss_streak": 4,
      "name": "no_edge_12_plus"
    },
    {
      "picks": 104,
      "wins": 60,
      "losses": 44,
      "win_rate": 57.69,
      "staked": 102.25,
      "profit": 14.27,
      "roi": 13.95,
      "avg_odds": 1.999,
      "max_drawdown_units": 4.92,
      "longest_loss_streak": 4,
      "name": "edge_6.5_11.9"
    },
    {
      "picks": 70,
      "wins": 34,
      "losses": 36,
      "win_rate": 48.57,
      "staked": 90.5,
      "profit": 11.67,
      "roi": 12.89,
      "avg_odds": 2.333,
      "max_drawdown_units": 5.5,
      "longest_loss_streak": 4,
      "name": "challenger_odds_2.10_2.70"
    },
    {
      "picks": 93,
      "wins": 55,
      "losses": 38,
      "win_rate": 59.14,
      "staked": 96.25,
      "profit": 12.19,
      "roi": 12.66,
      "avg_odds": 1.88,
      "max_drawdown_units": 4.61,
      "longest_loss_streak": 4,
      "name": "odds_1.70_2.09_no_top_rated"
    },
    {
      "picks": 116,
      "wins": 60,
      "losses": 56,
      "win_rate": 51.72,
      "staked": 143.5,
      "profit": 18.1,
      "roi": 12.61,
      "avg_odds": 2.228,
      "max_drawdown_units": 7.76,
      "longest_loss_streak": 4,
      "name": "challenger_only"
    },
    {
      "picks": 101,
      "wins": 59,
      "losses": 42,
      "win_rate": 58.42,
      "staked": 108.25,
      "profit": 11.84,
      "roi": 10.94,
      "avg_odds": 1.885,
      "max_drawdown_units": 4.61,
      "longest_loss_streak": 4,
      "name": "odds_1.70_2.09"
    },
    {
      "picks": 80,
      "wins": 46,
      "losses": 34,
      "win_rate": 57.5,
      "staked": 80.0,
      "profit": 6.56,
      "roi": 8.21,
      "avg_odds": 1.869,
      "max_drawdown_units": 5.86,
      "longest_loss_streak": 4,
      "name": "gold_zone"
    },
    {
      "picks": 83,
      "wins": 48,
      "losses": 35,
      "win_rate": 57.83,
      "staked": 89.0,
      "profit": 7.25,
      "roi": 8.15,
      "avg_odds": 1.854,
      "max_drawdown_units": 5.48,
      "longest_loss_streak": 4,
      "name": "favorite_odds_1.70_2.09"
    },
    {
      "picks": 34,
      "wins": 20,
      "losses": 14,
      "win_rate": 58.82,
      "staked": 38.5,
      "profit": 2.99,
      "roi": 7.78,
      "avg_odds": 1.879,
      "max_drawdown_units": 4.0,
      "longest_loss_streak": 3,
      "name": "challenger_odds_1.70_2.09"
    },
    {
      "picks": 66,
      "wins": 38,
      "losses": 28,
      "win_rate": 57.58,
      "staked": 65.75,
      "profit": 4.55,
      "roi": 6.92,
      "avg_odds": 1.835,
      "max_drawdown_units": 5.86,
      "longest_loss_streak": 4,
      "name": "brutal_conservative"
    },
    {
      "picks": 85,
      "wins": 49,
      "losses": 36,
      "win_rate": 57.65,
      "staked": 91.25,
      "profit": 6.27,
      "roi": 6.87,
      "avg_odds": 1.85,
      "max_drawdown_units": 5.82,
      "longest_loss_streak": 4,
      "name": "favorites_only"
    },
    {
      "picks": 296,
      "wins": 137,
      "losses": 159,
      "win_rate": 46.28,
      "staked": 339.75,
      "profit": 2.99,
      "roi": 0.88,
      "avg_odds": 2.258,
      "max_drawdown_units": 17.83,
      "longest_loss_streak": 9,
      "name": "no_top_rated"
    }
  ],
  "strategy_search": [
    {
      "picks": 12,
      "wins": 9,
      "losses": 3,
      "win_rate": 75.0,
      "staked": 13.0,
      "profit": 4.98,
      "roi": 38.31,
      "avg_odds": 1.846,
      "max_drawdown_units": 1.34,
      "longest_loss_streak": 1,
      "name": "wta_favorite_odds_1.70_2.09_no_top_rated"
    },
    {
      "picks": 13,
      "wins": 9,
      "losses": 4,
      "win_rate": 69.23,
      "staked": 14.5,
      "profit": 3.48,
      "roi": 24.0,
      "avg_odds": 1.854,
      "max_drawdown_units": 2.84,
      "longest_loss_streak": 2,
      "name": "wta_favorite_odds_1.70_2.09"
    },
    {
      "picks": 14,
      "wins": 9,
      "losses": 5,
      "win_rate": 64.29,
      "staked": 16.25,
      "profit": 3.55,
      "roi": 21.85,
      "avg_odds": 1.877,
      "max_drawdown_units": 2.5,
      "longest_loss_streak": 2,
      "name": "atp_favorite_odds_1.70_2.09"
    },
    {
      "picks": 45,
      "wins": 24,
      "losses": 21,
      "win_rate": 53.33,
      "staked": 60.25,
      "profit": 12.47,
      "roi": 20.7,
      "avg_odds": 2.244,
      "max_drawdown_units": 4.34,
      "longest_loss_streak": 3,
      "name": "challenger_underdog_odds_2.10_2.39_edge_12_plus"
    },
    {
      "picks": 28,
      "wins": 15,
      "losses": 13,
      "win_rate": 53.57,
      "staked": 35.0,
      "profit": 7.06,
      "roi": 20.18,
      "avg_odds": 2.238,
      "max_drawdown_units": 5.0,
      "longest_loss_streak": 4,
      "name": "challenger_underdog_odds_2.10_2.39_strong_only"
    },
    {
      "picks": 47,
      "wins": 24,
      "losses": 23,
      "win_rate": 51.06,
      "staked": 62.5,
      "profit": 10.22,
      "roi": 16.36,
      "avg_odds": 2.241,
      "max_drawdown_units": 5.25,
      "longest_loss_streak": 4,
      "name": "challenger_underdog_odds_2.10_2.39"
    },
    {
      "picks": 30,
      "wins": 15,
      "losses": 15,
      "win_rate": 50.0,
      "staked": 37.0,
      "profit": 5.06,
      "roi": 13.68,
      "avg_odds": 2.228,
      "max_drawdown_units": 6.0,
      "longest_loss_streak": 5,
      "name": "challenger_underdog_odds_2.10_2.39_no_top_rated"
    },
    {
      "picks": 66,
      "wins": 32,
      "losses": 34,
      "win_rate": 48.48,
      "staked": 86.75,
      "profit": 11.64,
      "roi": 13.41,
      "avg_odds": 2.332,
      "max_drawdown_units": 5.5,
      "longest_loss_streak": 4,
      "name": "challenger_underdog_odds_2.10_2.70_edge_12_plus"
    },
    {
      "picks": 70,
      "wins": 34,
      "losses": 36,
      "win_rate": 48.57,
      "staked": 90.5,
      "profit": 11.67,
      "roi": 12.89,
      "avg_odds": 2.333,
      "max_drawdown_units": 5.5,
      "longest_loss_streak": 4,
      "name": "challenger_underdog_odds_2.10_2.70"
    },
    {
      "picks": 20,
      "wins": 12,
      "losses": 8,
      "win_rate": 60.0,
      "staked": 20.75,
      "profit": 1.49,
      "roi": 7.19,
      "avg_odds": 1.805,
      "max_drawdown_units": 3.25,
      "longest_loss_streak": 3,
      "name": "challenger_favorite_odds_1.70_2.09_edge_under_12"
    },
    {
      "picks": 52,
      "wins": 24,
      "losses": 28,
      "win_rate": 46.15,
      "staked": 63.5,
      "profit": 4.4,
      "roi": 6.94,
      "avg_odds": 2.355,
      "max_drawdown_units": 5.45,
      "longest_loss_streak": 4,
      "name": "challenger_underdog_odds_2.10_2.70_no_top_rated"
    },
    {
      "picks": 48,
      "wins": 22,
      "losses": 26,
      "win_rate": 45.83,
      "staked": 60.0,
      "profit": 4.12,
      "roi": 6.87,
      "avg_odds": 2.359,
      "max_drawdown_units": 5.0,
      "longest_loss_streak": 4,
      "name": "challenger_underdog_odds_2.10_2.70_strong_only"
    },
    {
      "picks": 22,
      "wins": 13,
      "losses": 9,
      "win_rate": 59.09,
      "staked": 23.25,
      "profit": 1.37,
      "roi": 5.88,
      "avg_odds": 1.815,
      "max_drawdown_units": 3.25,
      "longest_loss_streak": 3,
      "name": "challenger_favorite_odds_1.70_2.09_no_top_rated"
    },
    {
      "picks": 23,
      "wins": 10,
      "losses": 13,
      "win_rate": 43.48,
      "staked": 28.0,
      "profit": 1.44,
      "roi": 5.15,
      "avg_odds": 2.522,
      "max_drawdown_units": 7.48,
      "longest_loss_streak": 5,
      "name": "challenger_underdog_odds_2.40_2.70"
    },
    {
      "picks": 26,
      "wins": 15,
      "losses": 11,
      "win_rate": 57.69,
      "staked": 29.25,
      "profit": 1.13,
      "roi": 3.85,
      "avg_odds": 1.832,
      "max_drawdown_units": 4.0,
      "longest_loss_streak": 3,
      "name": "challenger_favorite_odds_1.70_2.09"
    },
    {
      "picks": 19,
      "wins": 10,
      "losses": 9,
      "win_rate": 52.63,
      "staked": 18.75,
      "profit": 0.12,
      "roi": 0.64,
      "avg_odds": 1.819,
      "max_drawdown_units": 3.25,
      "longest_loss_streak": 3,
      "name": "itf_favorite_odds_1.70_1.89"
    },
    {
      "picks": 19,
      "wins": 10,
      "losses": 9,
      "win_rate": 52.63,
      "staked": 18.75,
      "profit": 0.12,
      "roi": 0.64,
      "avg_odds": 1.819,
      "max_drawdown_units": 3.25,
      "longest_loss_streak": 3,
      "name": "itf_favorite_odds_1.70_1.89_no_top_rated"
    },
    {
      "picks": 27,
      "wins": 11,
      "losses": 16,
      "win_rate": 40.74,
      "staked": 33.75,
      "profit": 0.19,
      "roi": 0.56,
      "avg_odds": 2.456,
      "max_drawdown_units": 5.54,
      "longest_loss_streak": 4,
      "name": "atp_underdog_odds_2.10_2.70_strong_only"
    },
    {
      "picks": 18,
      "wins": 7,
      "losses": 11,
      "win_rate": 38.89,
      "staked": 22.5,
      "profit": -0.05,
      "roi": -0.22,
      "avg_odds": 2.552,
      "max_drawdown_units": 5.0,
      "longest_loss_streak": 4,
      "name": "atp_underdog_odds_2.40_2.70_edge_12_plus"
    },
    {
      "picks": 18,
      "wins": 7,
      "losses": 11,
      "win_rate": 38.89,
      "staked": 22.5,
      "profit": -0.05,
      "roi": -0.22,
      "avg_odds": 2.552,
      "max_drawdown_units": 5.0,
      "longest_loss_streak": 4,
      "name": "atp_underdog_odds_2.40_2.70_strong_only"
    },
    {
      "picks": 18,
      "wins": 10,
      "losses": 8,
      "win_rate": 55.56,
      "staked": 19.0,
      "profit": -0.11,
      "roi": -0.61,
      "avg_odds": 1.792,
      "max_drawdown_units": 3.25,
      "longest_loss_streak": 3,
      "name": "challenger_favorite_odds_1.70_1.89"
    },
    {
      "picks": 18,
      "wins": 10,
      "losses": 8,
      "win_rate": 55.56,
      "staked": 19.0,
      "profit": -0.11,
      "roi": -0.61,
      "avg_odds": 1.792,
      "max_drawdown_units": 3.25,
      "longest_loss_streak": 3,
      "name": "challenger_favorite_odds_1.70_1.89_edge_under_12"
    },
    {
      "picks": 18,
      "wins": 10,
      "losses": 8,
      "win_rate": 55.56,
      "staked": 19.0,
      "profit": -0.11,
      "roi": -0.61,
      "avg_odds": 1.792,
      "max_drawdown_units": 3.25,
      "longest_loss_streak": 3,
      "name": "challenger_favorite_odds_1.70_1.89_no_top_rated"
    },
    {
      "picks": 22,
      "wins": 9,
      "losses": 13,
      "win_rate": 40.91,
      "staked": 26.5,
      "profit": -0.66,
      "roi": -2.48,
      "avg_odds": 2.527,
      "max_drawdown_units": 7.48,
      "longest_loss_streak": 5,
      "name": "challenger_underdog_odds_2.40_2.70_no_top_rated"
    },
    {
      "picks": 30,
      "wins": 15,
      "losses": 15,
      "win_rate": 50.0,
      "staked": 29.0,
      "profit": -0.9,
      "roi": -3.11,
      "avg_odds": 1.861,
      "max_drawdown_units": 5.89,
      "longest_loss_streak": 4,
      "name": "itf_favorite_odds_1.70_2.09"
    },
    {
      "picks": 30,
      "wins": 15,
      "losses": 15,
      "win_rate": 50.0,
      "staked": 29.0,
      "profit": -0.9,
      "roi": -3.11,
      "avg_odds": 1.861,
      "max_drawdown_units": 5.89,
      "longest_loss_streak": 4,
      "name": "itf_favorite_odds_1.70_2.09_no_top_rated"
    },
    {
      "picks": 21,
      "wins": 8,
      "losses": 13,
      "win_rate": 38.1,
      "staked": 26.5,
      "profit": -0.84,
      "roi": -3.16,
      "avg_odds": 2.522,
      "max_drawdown_units": 8.64,
      "longest_loss_streak": 6,
      "name": "challenger_underdog_odds_2.40_2.70_edge_12_plus"
    },
    {
      "picks": 21,
      "wins": 8,
      "losses": 13,
      "win_rate": 38.1,
      "staked": 26.25,
      "profit": -1.03,
      "roi": -3.9,
      "avg_odds": 2.53,
      "max_drawdown_units": 9.85,
      "longest_loss_streak": 5,
      "name": "itf_underdog_odds_2.40_2.70_strong_only"
    },
    {
      "picks": 26,
      "wins": 10,
      "losses": 16,
      "win_rate": 38.46,
      "staked": 31.0,
      "profit": -1.29,
      "roi": -4.17,
      "avg_odds": 2.526,
      "max_drawdown_units": 10.22,
      "longest_loss_streak": 4,
      "name": "itf_underdog_odds_2.40_2.70"
    },
    {
      "picks": 26,
      "wins": 10,
      "losses": 16,
      "win_rate": 38.46,
      "staked": 31.0,
      "profit": -1.29,
      "roi": -4.17,
      "avg_odds": 2.526,
      "max_drawdown_units": 10.22,
      "longest_loss_streak": 4,
      "name": "itf_underdog_odds_2.40_2.70_no_top_rated"
    },
    {
      "picks": 75,
      "wins": 30,
      "losses": 45,
      "win_rate": 40.0,
      "staked": 92.25,
      "profit": -6.42,
      "roi": -6.95,
      "avg_odds": 2.329,
      "max_drawdown_units": 14.65,
      "longest_loss_streak": 9,
      "name": "itf_underdog_odds_2.10_2.70"
    },
    {
      "picks": 49,
      "wins": 20,
      "losses": 29,
      "win_rate": 40.82,
      "staked": 61.25,
      "profit": -5.12,
      "roi": -8.36,
      "avg_odds": 2.224,
      "max_drawdown_units": 8.1,
      "longest_loss_streak": 6,
      "name": "itf_underdog_odds_2.10_2.39"
    },
    {
      "picks": 31,
      "wins": 11,
      "losses": 20,
      "win_rate": 35.48,
      "staked": 37.5,
      "profit": -3.56,
      "roi": -9.5,
      "avg_odds": 2.457,
      "max_drawdown_units": 7.29,
      "longest_loss_streak": 5,
      "name": "atp_underdog_odds_2.10_2.70_no_top_rated"
    },
    {
      "picks": 46,
      "wins": 18,
      "losses": 28,
      "win_rate": 39.13,
      "staked": 58.25,
      "profit": -6.02,
      "roi": -10.33,
      "avg_odds": 2.223,
      "max_drawdown_units": 8.26,
      "longest_loss_streak": 6,
      "name": "itf_underdog_odds_2.10_2.39_edge_12_plus"
    },
    {
      "picks": 17,
      "wins": 7,
      "losses": 10,
      "win_rate": 41.18,
      "staked": 19.75,
      "profit": -2.11,
      "roi": -10.71,
      "avg_odds": 2.395,
      "max_drawdown_units": 4.0,
      "longest_loss_streak": 3,
      "name": "wta_underdog_odds_2.10_2.70_no_top_rated"
    },
    {
      "picks": 70,
      "wins": 27,
      "losses": 43,
      "win_rate": 38.57,
      "staked": 84.75,
      "profit": -9.29,
      "roi": -10.97,
      "avg_odds": 2.334,
      "max_drawdown_units": 16.71,
      "longest_loss_streak": 9,
      "name": "itf_underdog_odds_2.10_2.70_no_top_rated"
    },
    {
      "picks": 21,
      "wins": 7,
      "losses": 14,
      "win_rate": 33.33,
      "staked": 25.25,
      "profit": -2.8,
      "roi": -11.09,
      "avg_odds": 2.546,
      "max_drawdown_units": 6.03,
      "longest_loss_streak": 5,
      "name": "atp_underdog_odds_2.40_2.70"
    },
    {
      "picks": 21,
      "wins": 7,
      "losses": 14,
      "win_rate": 33.33,
      "staked": 25.25,
      "profit": -2.8,
      "roi": -11.09,
      "avg_odds": 2.546,
      "max_drawdown_units": 6.03,
      "longest_loss_streak": 5,
      "name": "atp_underdog_odds_2.40_2.70_no_top_rated"
    },
    {
      "picks": 70,
      "wins": 26,
      "losses": 44,
      "win_rate": 37.14,
      "staked": 87.5,
      "profit": -10.05,
      "roi": -11.48,
      "avg_odds": 2.326,
      "max_drawdown_units": 17.22,
      "longest_loss_streak": 9,
      "name": "itf_underdog_odds_2.10_2.70_edge_12_plus"
    },
    {
      "picks": 20,
      "wins": 7,
      "losses": 13,
      "win_rate": 35.0,
      "staked": 25.0,
      "profit": -2.94,
      "roi": -11.75,
      "avg_odds": 2.528,
      "max_drawdown_units": 8.64,
      "longest_loss_streak": 6,
      "name": "challenger_underdog_odds_2.40_2.70_strong_only"
    },
    {
      "picks": 61,
      "wins": 23,
      "losses": 38,
      "win_rate": 37.7,
      "staked": 76.25,
      "profit": -9.18,
      "roi": -12.03,
      "avg_odds": 2.327,
      "max_drawdown_units": 15.45,
      "longest_loss_streak": 8,
      "name": "itf_underdog_odds_2.10_2.70_strong_only"
    },
    {
      "picks": 17,
      "wins": 8,
      "losses": 9,
      "win_rate": 47.06,
      "staked": 16.25,
      "profit": -2.05,
      "roi": -12.65,
      "avg_odds": 1.813,
      "max_drawdown_units": 4.35,
      "longest_loss_streak": 3,
      "name": "itf_favorite_odds_1.70_1.89_edge_under_12"
    },
    {
      "picks": 44,
      "wins": 16,
      "losses": 28,
      "win_rate": 36.36,
      "staked": 59.5,
      "profit": -7.58,
      "roi": -12.74,
      "avg_odds": 2.391,
      "max_drawdown_units": 12.03,
      "longest_loss_streak": 8,
      "name": "atp_underdog_odds_2.10_2.70_edge_12_plus"
    },
    {
      "picks": 24,
      "wins": 8,
      "losses": 16,
      "win_rate": 33.33,
      "staked": 29.25,
      "profit": -4.03,
      "roi": -13.76,
      "avg_odds": 2.524,
      "max_drawdown_units": 11.85,
      "longest_loss_streak": 7,
      "name": "itf_underdog_odds_2.40_2.70_edge_12_plus"
    },
    {
      "picks": 44,
      "wins": 17,
      "losses": 27,
      "win_rate": 38.64,
      "staked": 53.75,
      "profit": -8.0,
      "roi": -14.89,
      "avg_odds": 2.22,
      "max_drawdown_units": 8.52,
      "longest_loss_streak": 6,
      "name": "itf_underdog_odds_2.10_2.39_no_top_rated"
    },
    {
      "picks": 49,
      "wins": 17,
      "losses": 32,
      "win_rate": 34.69,
      "staked": 64.5,
      "profit": -9.68,
      "roi": -15.01,
      "avg_odds": 2.396,
      "max_drawdown_units": 14.26,
      "longest_loss_streak": 9,
      "name": "atp_underdog_odds_2.10_2.70"
    },
    {
      "picks": 40,
      "wins": 15,
      "losses": 25,
      "win_rate": 37.5,
      "staked": 50.0,
      "profit": -8.15,
      "roi": -16.3,
      "avg_odds": 2.22,
      "max_drawdown_units": 8.73,
      "longest_loss_streak": 5,
      "name": "itf_underdog_odds_2.10_2.39_strong_only"
    },
    {
      "picks": 27,
      "wins": 12,
      "losses": 15,
      "win_rate": 44.44,
      "staked": 25.25,
      "profit": -4.32,
      "roi": -17.09,
      "avg_odds": 1.856,
      "max_drawdown_units": 6.0,
      "longest_loss_streak": 4,
      "name": "itf_favorite_odds_1.70_2.09_edge_under_12"
    },
    {
      "picks": 28,
      "wins": 10,
      "losses": 18,
      "win_rate": 35.71,
      "staked": 39.25,
      "profit": -6.88,
      "roi": -17.54,
      "avg_odds": 2.283,
      "max_drawdown_units": 11.46,
      "longest_loss_streak": 7,
      "name": "atp_underdog_odds_2.10_2.39"
    },
    {
      "picks": 13,
      "wins": 6,
      "losses": 7,
      "win_rate": 46.15,
      "staked": 10.75,
      "profit": -1.9,
      "roi": -17.67,
      "avg_odds": 1.858,
      "max_drawdown_units": 4.25,
      "longest_loss_streak": 5,
      "name": "itf_favorite_odds_1.70_2.09_edge_6.5_7.9"
    },
    {
      "picks": 26,
      "wins": 9,
      "losses": 17,
      "win_rate": 34.62,
      "staked": 37.0,
      "profit": -7.53,
      "roi": -20.36,
      "avg_odds": 2.279,
      "max_drawdown_units": 11.49,
      "longest_loss_streak": 7,
      "name": "atp_underdog_odds_2.10_2.39_edge_12_plus"
    },
    {
      "picks": 13,
      "wins": 4,
      "losses": 9,
      "win_rate": 30.77,
      "staked": 16.25,
      "profit": -4.62,
      "roi": -28.46,
      "avg_odds": 2.408,
      "max_drawdown_units": 6.31,
      "longest_loss_streak": 4,
      "name": "wta_underdog_odds_2.10_2.70_strong_only"
    },
    {
      "picks": 16,
      "wins": 5,
      "losses": 11,
      "win_rate": 31.25,
      "staked": 16.0,
      "profit": -6.62,
      "roi": -41.38,
      "avg_odds": 1.856,
      "max_drawdown_units": 7.45,
      "longest_loss_streak": 4,
      "name": "itf_favorite_odds_1.70_2.09_standard_only"
    },
    {
      "picks": 25,
      "wins": 7,
      "losses": 18,
      "win_rate": 28.0,
      "staked": 31.75,
      "profit": -14.11,
      "roi": -44.46,
      "avg_odds": 2.346,
      "max_drawdown_units": 15.8,
      "longest_loss_streak": 6,
      "name": "wta_underdog_odds_2.10_2.70"
    },
    {
      "picks": 15,
      "wins": 4,
      "losses": 11,
      "win_rate": 26.67,
      "staked": 19.5,
      "profit": -9.9,
      "roi": -50.78,
      "avg_odds": 2.228,
      "max_drawdown_units": 11.59,
      "longest_loss_streak": 5,
      "name": "wta_underdog_odds_2.10_2.39"
    },
    {
      "picks": 21,
      "wins": 4,
      "losses": 17,
      "win_rate": 19.05,
      "staked": 28.25,
      "profit": -16.62,
      "roi": -58.85,
      "avg_odds": 2.345,
      "max_drawdown_units": 18.31,
      "longest_loss_streak": 6,
      "name": "wta_underdog_odds_2.10_2.70_edge_12_plus"
    },
    {
      "picks": 12,
      "wins": 2,
      "losses": 10,
      "win_rate": 16.67,
      "staked": 16.75,
      "profit": -11.14,
      "roi": -66.49,
      "avg_odds": 2.226,
      "max_drawdown_units": 12.82,
      "longest_loss_streak": 6,
      "name": "wta_underdog_odds_2.10_2.39_edge_12_plus"
    }
  ],
  "calibration": {
    "65-69%": {
      "picks": 144,
      "avg_model_prob": 65.99,
      "actual_win_rate": 45.83,
      "gap": -20.16
    },
    "60-64%": {
      "picks": 139,
      "avg_model_prob": 60.34,
      "actual_win_rate": 42.45,
      "gap": -17.9
    },
    "70-74%": {
      "picks": 2,
      "avg_model_prob": 74.0,
      "actual_win_rate": 0.0,
      "gap": -74.0
    },
    "55-59%": {
      "picks": 38,
      "avg_model_prob": 57.43,
      "actual_win_rate": 42.11,
      "gap": -15.32
    },
    "50-54%": {
      "picks": 19,
      "avg_model_prob": 52.57,
      "actual_win_rate": 68.42,
      "gap": 15.85
    },
    "45-49%": {
      "picks": 9,
      "avg_model_prob": 47.7,
      "actual_win_rate": 44.44,
      "gap": -3.25
    },
    "40-44%": {
      "picks": 3,
      "avg_model_prob": 43.98,
      "actual_win_rate": 66.67,
      "gap": 22.69
    }
  },
  "duplicates": {
    "same_match_same_bet": [
      {
        "key": "2026-05-05 | M. Timofeeva - N. Noha Akugue | N. Noha Akugue",
        "count": 2,
        "profit": -3.0
      },
      {
        "key": "2026-05-05 | A. Barrena - A. Holmgren | A. Holmgren",
        "count": 2,
        "profit": 3.49
      },
      {
        "key": "2026-05-05 | H. Dellien - J. De Jong | H. Dellien",
        "count": 2,
        "profit": -2.75
      },
      {
        "key": "2026-05-05 | L. Castelnuovo - O. Milic | L. Castelnuovo",
        "count": 2,
        "profit": -2.5
      },
      {
        "key": "2026-05-06 | J. C. Prado Angelo - B. Gadamauri | B. Gadamauri",
        "count": 3,
        "profit": -3.75
      },
      {
        "key": "2026-05-06 | J. Shin - L. Podgorichani | J. Shin",
        "count": 2,
        "profit": -2.75
      },
      {
        "key": "2026-05-06 | A. Eala - M. Frech | A. Eala",
        "count": 2,
        "profit": 2.03
      }
    ],
    "same_match_multiple_picks": [
      {
        "key": "2026-05-05 | M. Timofeeva - N. Noha Akugue",
        "count": 2,
        "profit": -3.0
      },
      {
        "key": "2026-05-05 | A. Barrena - A. Holmgren",
        "count": 2,
        "profit": 3.49
      },
      {
        "key": "2026-05-05 | H. Dellien - J. De Jong",
        "count": 2,
        "profit": -2.75
      },
      {
        "key": "2026-05-05 | L. Castelnuovo - O. Milic",
        "count": 2,
        "profit": -2.5
      },
      {
        "key": "2026-05-06 | J. C. Prado Angelo - B. Gadamauri",
        "count": 3,
        "profit": -3.75
      },
      {
        "key": "2026-05-06 | J. Shin - L. Podgorichani",
        "count": 2,
        "profit": -2.75
      },
      {
        "key": "2026-05-06 | A. Eala - M. Frech",
        "count": 2,
        "profit": 2.03
      }
    ]
  }
}