{
  "generated_at": "2026-06-04T07:26:01.815889+02:00",
  "pending_checked": 28,
  "updated": 17,
  "still_pending": 11,
  "not_found": 0,
  "errors": [],
  "checked": [
    {
      "match": "M. Chazal - T. Sahtali",
      "event_key": 12125924,
      "status": "Walk Over",
      "winner": "First Player",
      "score": "-",
      "changed": false,
      "reason": "keep_pending_status:walk over"
    },
    {
      "match": "V. Milovanova - K. Pavlova",
      "event_key": 12127783,
      "status": "Walk Over",
      "winner": "First Player",
      "score": "-",
      "changed": false,
      "reason": "keep_pending_status:walk over"
    },
    {
      "match": "C. Ansari - A. Karunaratne",
      "event_key": 12127709,
      "status": "Walk Over",
      "winner": "First Player",
      "score": "-",
      "changed": false,
      "reason": "keep_pending_status:walk over"
    },
    {
      "match": "P. Carreno-Busta - J. Munar",
      "event_key": 12127844,
      "status": "Walk Over",
      "winner": "Second Player",
      "score": "-",
      "changed": false,
      "reason": "keep_pending_status:walk over"
    },
    {
      "match": "J. Wang - Y. Yang",
      "event_key": 12128538,
      "status": "Set 1",
      "winner": null,
      "score": "0 - 0",
      "changed": false,
      "reason": "keep_pending_status:set 1"
    },
    {
      "match": "I. Xilas - S. Vincent Ruggeri",
      "event_key": 12130388,
      "status": "Walk Over",
      "winner": "First Player",
      "score": "-",
      "changed": false,
      "reason": "keep_pending_status:walk over"
    },
    {
      "match": "A. De Minaur - A. Blockx",
      "event_key": 12130659,
      "status": "Walk Over",
      "winner": "First Player",
      "score": "-",
      "changed": false,
      "reason": "keep_pending_status:walk over"
    },
    {
      "match": "A. Martin - B. Ellis",
      "event_key": 12132440,
      "status": "Finished",
      "winner": "First Player",
      "score": "2 - 0",
      "changed": true,
      "reason": "settled"
    },
    {
      "match": "Y. Shimizu - D. Sweeny",
      "event_key": 12132442,
      "status": "Finished",
      "winner": "First Player",
      "score": "2 - 0",
      "changed": true,
      "reason": "settled"
    },
    {
      "match": "S. Shimabukuro - S. Mochizuki",
      "event_key": 12132325,
      "status": "Finished",
      "winner": "First Player",
      "score": "2 - 0",
      "changed": true,
      "reason": "settled"
    },
    {
      "match": "T. Preston - A. Dudeney",
      "event_key": 12132528,
      "status": "Interrupted",
      "winner": null,
      "score": "1 - 0",
      "changed": false,
      "reason": "keep_pending_status:interrupted"
    },
    {
      "match": "A. Tomljanovic - K. Swan",
      "event_key": 12132525,
      "status": "Retired",
      "winner": "Second Player",
      "score": "0 - 1",
      "changed": true,
      "reason": "void_status:retired"
    },
    {
      "match": "K. Fakih - L. Taylor",
      "event_key": 12132973,
      "status": "Finished",
      "winner": "First Player",
      "score": "2 - 0",
      "changed": true,
      "reason": "settled"
    },
    {
      "match": "C. Aulia - J. Chan",
      "event_key": 12132972,
      "status": "Finished",
      "winner": "Second Player",
      "score": "0 - 2",
      "changed": true,
      "reason": "settled"
    },
    {
      "match": "A. Raggi - D. Spiteri",
      "event_key": 12132933,
      "status": "Finished",
      "winner": "Second Player",
      "score": "0 - 2",
      "changed": true,
      "reason": "settled"
    },
    {
      "match": "A. Kalinskaya - M. Chwalinska",
      "event_key": 12132679,
      "status": "Finished",
      "winner": "Second Player",
      "score": "0 - 2",
      "changed": true,
      "reason": "settled"
    },
    {
      "match": "E. Ymer - C. O'Connell",
      "event_key": 12132753,
      "status": "Finished",
      "winner": "First Player",
      "score": "2 - 0",
      "changed": true,
      "reason": "settled"
    },
    {
      "match": "J. McCabe - K. Majchrzak",
      "event_key": 12132751,
      "status": "Finished",
      "winner": "Second Player",
      "score": "0 - 2",
      "changed": true,
      "reason": "settled"
    },
    {
      "match": "M. Dodig - G. Den Ouden",
      "event_key": 12132711,
      "status": "Finished",
      "winner": "Second Player",
      "score": "1 - 2",
      "changed": true,
      "reason": "settled"
    },
    {
      "match": "K. Kawa - M. Joint",
      "event_key": 12132910,
      "status": "Interrupted",
      "winner": null,
      "score": "0 - 0",
      "changed": false,
      "reason": "keep_pending_status:interrupted"
    },
    {
      "match": "L. Havlickova - Y. Kabbaj",
      "event_key": 12133146,
      "status": "",
      "winner": null,
      "score": "-",
      "changed": false,
      "reason": "keep_pending_status:unknown"
    },
    {
      "match": "H. Squire - P. Martinez",
      "event_key": 12133077,
      "status": "Finished",
      "winner": "First Player",
      "score": "2 - 0",
      "changed": true,
      "reason": "settled"
    },
    {
      "match": "P. Boscardin Dias - M. Mrva",
      "event_key": 12133102,
      "status": "Finished",
      "winner": "Second Player",
      "score": "0 - 2",
      "changed": true,
      "reason": "settled"
    },
    {
      "match": "Z. Zhang - O. Virtanen",
      "event_key": 12132752,
      "status": "Finished",
      "winner": "Second Player",
      "score": "0 - 2",
      "changed": true,
      "reason": "settled"
    },
    {
      "match": "E. Micic - I. Spink",
      "event_key": 12132925,
      "status": "Finished",
      "winner": "Second Player",
      "score": "0 - 2",
      "changed": true,
      "reason": "settled"
    },
    {
      "match": "M. Berrettini - M. Arnaldi",
      "event_key": 12133000,
      "status": "Retired",
      "winner": "Second Player",
      "score": "0 - 1",
      "changed": true,
      "reason": "void_status:retired"
    },
    {
      "match": "R. Montgomery - L. Boskovic",
      "event_key": 12133144,
      "status": "",
      "winner": null,
      "score": "-",
      "changed": false,
      "reason": "keep_pending_status:unknown"
    },
    {
      "match": "G. Price - L. Fullana",
      "event_key": 12133378,
      "status": "Finished",
      "winner": "Second Player",
      "score": "0 - 2",
      "changed": true,
      "reason": "settled"
    }
  ]
}
